<?xml version="1.0" standalone="yes"?>

<animation frameRate="30">

  <frame>
    <transform name="bison" translation="-529.682, 341.794, -38.2763" rotation="0.0, 9.28547e-007, 0.0, 1.0" scale="35.5709, 28.4567, 28.4567"/>
    <transform name="Omni03" translation="-1642.78, -3829.81, -4202.06" rotation="0.0, 0.0, 0.0, 1.0" scale="34.5, 34.5, 34.5"/>
    <transform name="Omni05" translation="-3561.19, 3757.06, -2462.9" rotation="0.0, 0.0, 0.0, 1.0" scale="34.5, 34.5, 34.5"/>
    <transform name="Omni06" translation="4739.17, 2891.95, 11806.9" rotation="0.0, 0.0, 0.0, 1.0" scale="34.5, 34.5, 34.5"/>
    <transform name="Omni07" translation="13411.8, 5143.02, -2619.83" rotation="0.0, 0.0, 0.0, 1.0" scale="34.5, 34.5, 34.5"/>
    <transform name="Omni08" translation="-18659.1, 6889.32, 1469.94" rotation="0.0, 0.0, 0.0, 1.0" scale="34.5, 34.5, 34.5"/>
    <transform name="Omni09" translation="2752.18, -15860.6, 10088.9" rotation="0.0, 0.0, 0.0, 1.0" scale="34.5, 34.5, 34.5"/>
    <transform name="Bip01" translation="-0.165566, 88.3778, 90.4749" rotation="0.50005, 0.49995, -0.499949, 0.500051" scale="1.0, 1.0, 1.0"/>
    <transform name="Bip01 Footsteps" translation="74.5764, -0.0150956, -9.37528e-006" rotation="-0.50005, -0.49995, 0.499949, 0.500051" scale="1.0, 1.0, 1.0"/>
    <transform name="Bip01 Pelvis" translation="2.65669, 1.46929, -5.56298e-007" rotation="-0.488201, -0.488201, -0.511526, 0.511527" scale="1.0, 1.0, 1.0"/>
    <transform name="Bip01 Spine" translation="23.8976, -1.44507, 1.11561" rotation="0.00126782, -0.00393294, 0.0381052, 0.999265" scale="1.0, 1.0, 1.0"/>
    <transform name="Bip01 Spine1" translation="35.5192, -0.0276929, -4.00289e-005" rotation="0.000267621, -0.00424196, -0.102063, 0.994769" scale="1.0, 1.0, 1.0"/>
    <transform name="Bip01 Spine2" translation="35.5236, -0.0265814, -9.6262e-005" rotation="0.00140662, -0.0150146, -0.0259754, 0.999549" scale="1.0, 1.0, 1.0"/>
    <transform name="Bip01 Neck" translation="33.4221, -0.00970221, 0.0" rotation="2.37721e-007, 1.24462e-006, 0.216669, 0.976245" scale="1.0, 1.0, 1.0"/>
    <transform name="Bip01 Neck1" translation="13.4472, -0.00923569, -9.28285e-007" rotation="7.01172e-006, 0.000107677, 0.26237, 0.964967" scale="1.0, 1.0, 1.0"/>
    <transform name="Bip01 Head" translation="13.4417, 2.94443e-006, 0.0" rotation="-0.0044913, 0.00155306, -0.397173, 0.917732" scale="1.0, 1.0, 1.0"/>
    <transform name="Bip01 HeadNub" translation="41.8745, 5.53209e-006, 0.0" rotation="0.0, 0.0, 0.0, 1.0" scale="1.0, 1.0, 1.0"/>
    <transform name="Bip01 Ponytail1" translation="1.85175, 47.522, 0.000133774" rotation="0.00165862, -0.00125825, 0.683872, 0.729599" scale="1.0, 1.0, 1.0"/>
    <transform name="Bip01 Ponytail11" translation="12.6779, -0.010087, -7.2122e-006" rotation="0.000328523, -0.00205459, -0.0109214, 0.999938" scale="1.0, 1.0, 1.0"/>
    <transform name="Bip01 Ponytail1Nub" translation="12.6781, -2.21362e-006, 0.0" rotation="0.707388, 0.706825, 9.80228e-007, -9.81011e-007" scale="1.0, 1.0, 1.0"/>
    <transform name="Bip01 L Clavicle" translation="-8.19657, 3.36038, 32.4074" rotation="0.533521, 0.401559, 0.579686, 0.46698" scale="1.0, 1.0, 1.0"/>
    <transform name="Bip01 L UpperArm" translation="33.0219, 1.46498e-007, -1.33406e-006" rotation="-0.678496, -0.0625022, -0.283333, 0.674877" scale="1.0, 1.0, 1.0"/>
    <transform name="Bip01 L Forearm" translation="22.361, 3.02253e-007, 2.20413e-006" rotation="0.0, 0.0, -0.0903644, 0.995909" scale="1.0, 1.0, 1.0"/>
    <transform name="Bip01 L Hand" translation="31.134, 1.80585e-006, -2.91431e-006" rotation="-0.00697215, 0.0109947, -0.211983, 0.977187" scale="1.0, 1.0, 1.0"/>
    <transform name="Bip01 L Finger0" translation="12.825, -0.714874, -4.0374" rotation="0.0612045, -0.0209451, 0.437685, 0.896798" scale="1.0, 1.0, 1.0"/>
    <transform name="Bip01 L Finger0Nub" translation="9.28433, 5.81897e-007, -3.15916e-006" rotation="0.0, 0.0, 0.0, 1.0" scale="1.0, 1.0, 1.0"/>
    <transform name="Bip01 R Clavicle" translation="-8.19635, 3.36048, -32.4075" rotation="-0.532295, -0.40648, 0.575662, 0.469094" scale="1.0, 1.0, 1.0"/>
    <transform name="Bip01 R UpperArm" translation="33.0219, -1.07973e-006, -1.45429e-006" rotation="0.556252, -0.296891, 0.223696, 0.743236" scale="1.0, 1.0, 1.0"/>
    <transform name="Bip01 R Forearm" translation="22.361, -9.38872e-007, -2.32925e-007" rotation="0.0, 0.0, -0.549875, 0.835247" scale="1.0, 1.0, 1.0"/>
    <transform name="Bip01 R Hand" translation="31.134, 4.7154e-007, 1.49854e-006" rotation="-0.00169103, -0.00616775, 0.0589317, 0.998242" scale="1.0, 1.0, 1.0"/>
    <transform name="Bip01 R Finger0" translation="12.825, -0.71487, 4.0374" rotation="0.0416215, 0.00989103, 0.212582, 0.976206" scale="1.0, 1.0, 1.0"/>
    <transform name="Bip01 R Finger0Nub" translation="9.28433, -5.88558e-007, 1.53534e-006" rotation="0.0, 0.0, 1.0, 0.0" scale="1.0, 1.0, 1.0"/>
    <transform name="Bip01 L Thigh" translation="-23.5707, 3.30224, 18.6268" rotation="0.648793, 0.760064, 0.00901051, 0.035901" scale="1.0, 1.0, 1.0"/>
    <transform name="Bip01 L Calf" translation="44.7054, -5.31401e-006, -8.17473e-007" rotation="0.0, 0.0, -0.578369, 0.815776" scale="1.0, 1.0, 1.0"/>
    <transform name="Bip01 L HorseLink" translation="25.1575, 2.24417e-006, -1.30411e-006" rotation="0.0, 0.0, 0.564138, 0.82568" scale="1.0, 1.0, 1.0"/>
    <transform name="Bip01 L Foot" translation="19.0106, -7.26444e-007, 2.91875e-007" rotation="-0.000375839, 0.0142147, -0.463659, 0.8859" scale="1.0, 1.0, 1.0"/>
    <transform name="Bip01 L Toe0" translation="7.55725, 12.3023, 3.18802e-007" rotation="0.0, 0.0, 0.580703, 0.814115" scale="1.0, 1.0, 1.0"/>
    <transform name="Bip01 L Toe0Nub" translation="1.13738, 4.03891e-006, 1.31691e-006" rotation="0.0, 0.0, 1.0, 0.0" scale="1.0, 1.0, 1.0"/>
    <transform name="Bip01 R Thigh" translation="-23.882, 3.21478, -20.4951" rotation="0.527762, 0.849135, 0.00552603, 0.0201479" scale="1.0, 1.0, 1.0"/>
    <transform name="Bip01 R Calf" translation="44.7054, -5.04836e-006, 3.34077e-007" rotation="0.0, 0.0, -0.54422, 0.838943" scale="1.0, 1.0, 1.0"/>
    <transform name="Bip01 R HorseLink" translation="25.1575, -2.73177e-006, -6.63175e-007" rotation="0.0, 0.0, 0.607851, 0.794051" scale="1.0, 1.0, 1.0"/>
    <transform name="Bip01 R Foot" translation="19.0106, 3.36344e-006, 8.54394e-007" rotation="-0.00415448, 0.0123301, -0.539312, 0.842005" scale="1.0, 1.0, 1.0"/>
    <transform name="Bip01 R Toe0" translation="7.55725, 12.3023, 6.24413e-007" rotation="0.0, 0.0, 0.611307, 0.791394" scale="1.0, 1.0, 1.0"/>
    <transform name="Bip01 R Toe0Nub" translation="1.13738, -1.09626e-005, -1.63988e-007" rotation="0.0, 0.0, 0.0, 1.0" scale="1.0, 1.0, 1.0"/>
    <transform name="Bip01 Tail" translation="-43.9401, -1.15592, -1.68907" rotation="-0.0373178, 0.0334807, 0.984604, 0.167454" scale="1.0, 1.0, 1.0"/>
    <transform name="Bip01 Tail1" translation="12.2225, -0.00972723, -1.70822e-005" rotation="-0.000585966, -0.0561618, -0.0259675, 0.998084" scale="1.0, 1.0, 1.0"/>
    <transform name="Bip01 Tail2" translation="12.2209, -0.0110914, -1.33976e-005" rotation="-9.22957e-005, -0.00675819, -0.0936118, 0.995586" scale="1.0, 1.0, 1.0"/>
    <transform name="Bip01 Tail3" translation="14.1775, -0.0114644, 1.96435e-005" rotation="0.00351062, 0.080791, -0.0537317, 0.995275" scale="1.0, 1.0, 1.0"/>
    <transform name="Bip01 TailNub" translation="14.4946, -1.61886e-006, -3.2797e-007" rotation="0.707388, 0.706825, 9.79978e-007, -9.83682e-007" scale="1.0, 1.0, 1.0"/>
    <transform name="Bip02" translation="0.696283, 25.7588, 159.476" rotation="0.331966, 0.331967, -0.624338, 0.624339" scale="1.0, 1.0, 1.0"/>
    <transform name="Bip02 Footsteps" translation="29.8501, -5.47551e-006, -20.1341" rotation="-0.331966, -0.331967, 0.624338, 0.624339" scale="1.0, 1.0, 1.0"/>
    <transform name="Bip02 Pelvis" translation="-1.15583, 0.0, 2.53678e-006" rotation="-0.499999, -0.5, -0.5, 0.500001" scale="1.0, 1.0, 1.0"/>
    <transform name="Bip02 Spine" translation="9.85939, -0.00634468, -5.84761e-005" rotation="0.00560088, -0.00151297, 0.218192, 0.975889" scale="1.0, 1.0, 1.0"/>
    <transform name="Bip02 Spine1" translation="8.81453, -0.00864411, -0.000101255" rotation="0.00579746, 0.000265773, -0.107433, 0.994195" scale="1.0, 1.0, 1.0"/>
    <transform name="Bip02 Spine2" translation="11.102, -0.0112678, -0.000130712" rotation="0.0058034, 3.76818e-005, -0.00728551, 0.999957" scale="1.0, 1.0, 1.0"/>
    <transform name="Bip02 Neck" translation="14.1473, -0.00513635, -4.91018e-007" rotation="0.0, 3.32973e-007, -0.119973, 0.992777" scale="1.0, 1.0, 1.0"/>
    <transform name="Bip02 Head" translation="6.64599, -8.85425e-006, 0.0" rotation="-0.0154373, -0.00746232, -0.231351, 0.972719" scale="1.0, 1.0, 1.0"/>
    <transform name="Bip02 HeadNub" translation="36.1861, -5.09456e-007, 0.0" rotation="0.0, 0.0, 0.0, 1.0" scale="1.0, 1.0, 1.0"/>
    <transform name="Bip02 Ponytail1" translation="20.4786, -7.48921, -11.0866" rotation="0.0302618, 0.161136, -0.811112, 0.561441" scale="1.0, 1.0, 1.0"/>
    <transform name="Bip02 Ponytail11" translation="13.6632, -0.0110542, 0.000346168" rotation="-0.0200459, -0.0571479, -0.0791761, 0.995019" scale="1.0, 1.0, 1.0"/>
    <transform name="Bip02 Ponytail12" translation="14.0723, -0.00851815, 0.000530583" rotation="-0.0206994, -0.0494541, 0.176762, 0.982792" scale="1.0, 1.0, 1.0"/>
    <transform name="Bip02 Ponytail13" translation="11.4322, -0.0150654, 0.000938755" rotation="-0.0184206, -0.0478576, 0.215193, 0.975224" scale="1.0, 1.0, 1.0"/>
    <transform name="Bip02 Ponytail1Nub" translation="20.8677, -7.00616e-006, -5.0507e-007" rotation="0.707388, 0.706825, 9.83427e-007, -9.78892e-007" scale="1.0, 1.0, 1.0"/>
    <transform name="Bip02 Ponytail2" translation="21.3866, -5.37349, 12.0413" rotation="0.0307288, -0.153606, -0.728676, 0.666702" scale="1.0, 1.0, 1.0"/>
    <transform name="Bip02 Ponytail21" translation="14.6308, -0.0118038, -0.00128803" rotation="0.0728728, 0.109214, -0.187143, 0.973519" scale="1.0, 1.0, 1.0"/>
    <transform name="Bip02 Ponytail22" translation="16.1033, -0.0121652, -0.0029651" rotation="0.10089, 0.0840181, 0.165642, 0.977407" scale="1.0, 1.0, 1.0"/>
    <transform name="Bip02 Ponytail23" translation="16.5405, -0.0122284, -0.00286804" rotation="0.106839, 0.0763105, 0.0927519, 0.986995" scale="1.0, 1.0, 1.0"/>
    <transform name="Bip02 Ponytail2Nub" translation="15.9972, -3.60356e-006, 9.52038e-007" rotation="0.707388, 0.706825, 9.77663e-007, -9.74056e-007" scale="1.0, 1.0, 1.0"/>
    <transform name="Bip02 L Clavicle" translation="8.16744e-006, 0.00527042, 3.4594" rotation="0.539147, -0.130263, 0.80249, -0.219913" scale="1.0, 1.0, 1.0"/>
    <transform name="Bip02 L UpperArm" translation="14.6244, -1.59409e-005, -4.25865e-006" rotation="-0.115212, 0.162677, -0.664388, 0.720313" scale="1.0, 1.0, 1.0"/>
    <transform name="Bip02 L Forearm" translation="27.0198, 1.30837e-006, 2.30652e-006" rotation="0.0, 0.0, -0.681932, 0.731415" scale="1.0, 1.0, 1.0"/>
    <transform name="Bip02 L Hand" translation="18.529, -2.69566e-006, 4.93246e-006" rotation="-0.706826, -0.0370071, 1.4742e-005, 0.706419" scale="1.0, 1.0, 1.0"/>
    <transform name="Bip02 L Finger0" translation="5.43344, -0.00308057, -6.3906" rotation="0.72855, 0.509249, 0.023378, 0.45753" scale="1.0, 1.0, 1.0"/>
    <transform name="Bip02 L Finger01" translation="4.86919, 9.6268e-006, -7.73507e-006" rotation="0.0, 0.0, 0.321439, 0.94693" scale="1.0, 1.0, 1.0"/>
    <transform name="Bip02 L Finger0Nub" translation="5.85087, -2.23231e-006, 1.18522e-005" rotation="0.0, 0.0, 0.0, 1.0" scale="1.0, 1.0, 1.0"/>
    <transform name="Bip02 L Finger1" translation="12.6299, -1.21083, -4.22835" rotation="0.0283097, 0.0540893, 0.468574, 0.881312" scale="1.0, 1.0, 1.0"/>
    <transform name="Bip02 L Finger11" translation="4.71212, -1.72489e-006, -2.89796e-006" rotation="0.0, 0.0, 0.378649, 0.925541" scale="1.0, 1.0, 1.0"/>
    <transform name="Bip02 L Finger1Nub" translation="5.46606, -1.02657e-006, 5.49965e-006" rotation="0.0, 0.0, 0.0, 1.0" scale="1.0, 1.0, 1.0"/>
    <transform name="Bip02 L Finger2" translation="13.5902, 0.516083, 2.76274" rotation="-0.161864, 0.00222143, 0.350023, 0.922648" scale="1.0, 1.0, 1.0"/>
    <transform name="Bip02 L Finger21" translation="4.71932, -1.16557e-006, 1.12421e-005" rotation="0.0, 0.0, 0.378649, 0.925541" scale="1.0, 1.0, 1.0"/>
    <transform name="Bip02 L Finger2Nub" translation="5.89014, -7.57641e-007, -8.54749e-006" rotation="0.0, 0.0, 0.0, 1.0" scale="1.0, 1.0, 1.0"/>
    <transform name="Bip02 R Clavicle" translation="1.72958e-006, 0.00530017, -3.4594" rotation="-0.516613, -0.151245, 0.841545, -0.0451442" scale="1.0, 1.0, 1.0"/>
    <transform name="Bip02 R UpperArm" translation="14.6244, 1.27829e-005, -1.66803e-006" rotation="0.285105, 0.152946, -0.414996, 0.850353" scale="1.0, 1.0, 1.0"/>
    <transform name="Bip02 R Forearm" translation="27.0198, 4.86362e-007, 6.12628e-006" rotation="0.0, 0.0, -0.625881, 0.779918" scale="1.0, 1.0, 1.0"/>
    <transform name="Bip02 R Hand" translation="18.529, 1.11891e-006, -4.70482e-006" rotation="0.789028, 0.0348725, -0.0892093, 0.606845" scale="1.0, 1.0, 1.0"/>
    <transform name="Bip02 R Finger0" translation="5.43344, -0.00308031, 6.3906" rotation="-0.744948, -0.248646, -0.109343, 0.609321" scale="1.0, 1.0, 1.0"/>
    <transform name="Bip02 R Finger01" translation="4.86918, 2.63741e-006, 3.60399e-006" rotation="0.0, 0.0, 0.241922, 0.970296" scale="1.0, 1.0, 1.0"/>
    <transform name="Bip02 R Finger0Nub" translation="5.85087, -3.60979e-006, -7.84314e-006" rotation="0.0, 0.0, 1.0, 0.0" scale="1.0, 1.0, 1.0"/>
    <transform name="Bip02 R Finger1" translation="12.6299, -1.21083, 4.22834" rotation="-0.0271823, -0.0546645, 0.450205, 0.890836" scale="1.0, 1.0, 1.0"/>
    <transform name="Bip02 R Finger11" translation="4.71211, -3.76072e-006, -2.49419e-006" rotation="0.0, 0.0, 0.300706, 0.953717" scale="1.0, 1.0, 1.0"/>
    <transform name="Bip02 R Finger1Nub" translation="5.46605, 9.80625e-007, 3.78342e-006" rotation="0.0, 0.0, 1.0, 0.0" scale="1.0, 1.0, 1.0"/>
    <transform name="Bip02 R Finger2" translation="13.5902, 0.51608, -2.76274" rotation="0.0687152, 0.150272, 0.477307, 0.863061" scale="1.0, 1.0, 1.0"/>
    <transform name="Bip02 R Finger21" translation="4.71931, 6.36838e-007, 2.42554e-006" rotation="0.0, 0.0, 0.300706, 0.953717" scale="1.0, 1.0, 1.0"/>
    <transform name="Bip02 R Finger2Nub" translation="5.89014, -1.24129e-006, 1.51311e-006" rotation="0.0, 0.0, 1.0, 0.0" scale="1.0, 1.0, 1.0"/>
    <transform name="Bip02 L Thigh" translation="-8.86863, 4.29838, 9.12862" rotation="0.899996, 0.294766, 0.0316271, -0.31956" scale="1.0, 1.0, 1.0"/>
    <transform name="Bip02 L Calf" translation="27.795, 2.92995e-006, -1.47317e-006" rotation="0.0, 0.0, 0.869001, -0.49481" scale="1.0, 1.0, 1.0"/>
    <transform name="Bip02 L Foot" translation="29.6015, 3.88464e-006, 3.86308e-006" rotation="0.00011179, -0.189168, -0.0510069, 0.980619" scale="1.0, 1.0, 1.0"/>
    <transform name="Bip02 L Toe0" translation="14.534, 17.5771, -6.92374e-007" rotation="0.0, 0.0, 0.707107, 0.707107" scale="1.0, 1.0, 1.0"/>
    <transform name="Bip02 L Toe0Nub" translation="11.101, 6.58797e-007, 1.24729e-006" rotation="0.0, 0.0, 1.0, 0.0" scale="1.0, 1.0, 1.0"/>
    <transform name="Bip02 R Thigh" translation="-8.96711, 4.1109, -9.11862" rotation="0.902046, 0.302405, -0.147519, 0.270373" scale="1.0, 1.0, 1.0"/>
    <transform name="Bip02 R Calf" translation="27.795, -1.56132e-006, 1.63288e-006" rotation="0.0, 0.0, -0.85145, 0.524436" scale="1.0, 1.0, 1.0"/>
    <transform name="Bip02 R Foot" translation="29.6015, -4.7636e-006, 4.44624e-006" rotation="-0.0545446, -0.0663307, 0.0852781, 0.992649" scale="1.0, 1.0, 1.0"/>
    <transform name="Bip02 R Toe0" translation="14.534, 17.5771, 1.91565e-006" rotation="0.0, 0.0, 0.707107, 0.707107" scale="1.0, 1.0, 1.0"/>
    <transform name="Bip02 R Toe0Nub" translation="11.101, 7.69809e-007, 3.24976e-007" rotation="0.0, 0.0, 0.0, 1.0" scale="1.0, 1.0, 1.0"/>
    <transform name="Bip02 Tail" translation="-8.30417, -5.94255, 0.101986" rotation="0.0635621, 0.13547, 0.982239, 0.113197" scale="1.0, 1.0, 1.0"/>
    <transform name="Bip02 Tail1" translation="18.4105, -0.0135898, 0.000279673" rotation="-0.00875609, 0.0177503, -0.0773476, 0.996808" scale="1.0, 1.0, 1.0"/>
    <transform name="Bip02 Tail2" translation="17.2716, -0.013502, -0.00179189" rotation="0.0649872, 0.0225226, -0.26088, 0.962918" scale="1.0, 1.0, 1.0"/>
    <transform name="Bip02 TailNub" translation="19.829, 1.9725e-007, -1.02494e-006" rotation="0.707388, 0.706825, 9.83674e-007, -9.89778e-007" scale="1.0, 1.0, 1.0"/>
    <transform name="Bone01" translation="-1.02918, 10.6656, 0.0733637" rotation="0.634016, 0.425062, 0.273252, 0.585388" scale="1.0, 1.0, 1.0"/>
    <transform name="Bone02" translation="23.0916, 3.85494e-006, 6.14891e-006" rotation="0.0, 0.0, 0.0, 1.0" scale="1.0, 1.0, 1.0"/>
    <transform name="rider" translation="174.459, 3.32103, -13.7466" rotation="0.0, 0.0, 0.0, 1.0" scale="1.0, 1.0, 1.0"/>
  </frame>

  <frame>
    <transform name="bison" translation="-529.682, 341.794, -38.2763" rotation="0.0, 9.28547e-007, 0.0, 1.0" scale="35.5709, 28.4567, 28.4567"/>
    <transform name="Omni03" translation="-1642.78, -3829.81, -4202.06" rotation="0.0, 0.0, 0.0, 1.0" scale="34.5, 34.5, 34.5"/>
    <transform name="Omni05" translation="-3561.19, 3757.06, -2462.9" rotation="0.0, 0.0, 0.0, 1.0" scale="34.5, 34.5, 34.5"/>
    <transform name="Omni06" translation="4739.17, 2891.95, 11806.9" rotation="0.0, 0.0, 0.0, 1.0" scale="34.5, 34.5, 34.5"/>
    <transform name="Omni07" translation="13411.8, 5143.02, -2619.83" rotation="0.0, 0.0, 0.0, 1.0" scale="34.5, 34.5, 34.5"/>
    <transform name="Omni08" translation="-18659.1, 6889.32, 1469.94" rotation="0.0, 0.0, 0.0, 1.0" scale="34.5, 34.5, 34.5"/>
    <transform name="Omni09" translation="2752.18, -15860.6, 10088.9" rotation="0.0, 0.0, 0.0, 1.0" scale="34.5, 34.5, 34.5"/>
    <transform name="Bip01" translation="-0.165566, 88.3778, 74.6169" rotation="0.465823, 0.465763, -0.531982, 0.532043" scale="1.0, 1.0, 1.0"/>
    <transform name="Bip01 Footsteps" translation="58.2034, -0.00706026, -7.75954" rotation="-0.465823, -0.465763, 0.531982, 0.532043" scale="1.0, 1.0, 1.0"/>
    <transform name="Bip01 Pelvis" translation="-5.18202, 0.943647, -5.49064e-006" rotation="-0.491731, -0.491731, -0.508134, 0.508135" scale="1.0, 1.0, 1.0"/>
    <transform name="Bip01 Spine" translation="23.9139, -1.44465, 0.784633" rotation="0.00167076, -0.00375373, 0.093656, 0.995596" scale="1.0, 1.0, 1.0"/>
    <transform name="Bip01 Spine1" translation="35.5215, -0.0280738, -1.28022e-005" rotation="6.1384e-005, -0.00265486, -0.0613634, 0.998112" scale="1.0, 1.0, 1.0"/>
    <transform name="Bip01 Spine2" translation="35.525, -0.0266176, -6.77019e-005" rotation="0.00126987, -0.0098102, -3.86709e-005, 0.999951" scale="1.0, 1.0, 1.0"/>
    <transform name="Bip01 Neck" translation="33.4197, -0.0104831, 0.0" rotation="-2.82914e-007, -6.63379e-006, 0.100999, 0.994887" scale="1.0, 1.0, 1.0"/>
    <transform name="Bip01 Neck1" translation="13.4448, -0.0102571, -2.65004e-007" rotation="-1.35862e-007, 8.30217e-005, 0.144951, 0.989439" scale="1.0, 1.0, 1.0"/>
    <transform name="Bip01 Head" translation="13.4417, 5.38481e-006, 0.0" rotation="-0.0086955, 0.0011122, -0.356365, 0.934306" scale="1.0, 1.0, 1.0"/>
    <transform name="Bip01 HeadNub" translation="41.8745, -2.36401e-006, 0.0" rotation="0.0, 0.0, 0.0, 1.0" scale="1.0, 1.0, 1.0"/>
    <transform name="Bip01 Ponytail1" translation="1.85177, 47.5229, 9.05484e-005" rotation="0.0158141, -0.0119399, 0.716325, 0.697485" scale="1.0, 1.0, 1.0"/>
    <transform name="Bip01 Ponytail11" translation="12.6788, -0.0100726, -5.0121e-005" rotation="0.00316049, -0.0195605, 0.0347291, 0.9992" scale="1.0, 1.0, 1.0"/>
    <transform name="Bip01 Ponytail1Nub" translation="12.6781, 8.89893e-007, 0.0" rotation="0.707388, 0.706825, 9.81359e-007, -9.80244e-007" scale="1.0, 1.0, 1.0"/>
    <transform name="Bip01 L Clavicle" translation="-8.75, 1.36444, 32.4076" rotation="0.462467, 0.477383, 0.640568, 0.384582" scale="1.0, 1.0, 1.0"/>
    <transform name="Bip01 L UpperArm" translation="33.0219, -2.32762e-006, 2.12353e-007" rotation="-0.645652, -0.187953, -0.404584, 0.619773" scale="1.0, 1.0, 1.0"/>
    <transform name="Bip01 L Forearm" translation="22.361, -6.31216e-007, -2.12779e-006" rotation="0.0, 0.0, 0.0069986, 0.999976" scale="1.0, 1.0, 1.0"/>
    <transform name="Bip01 L Hand" translation="31.134, 3.02458e-006, 3.18621e-006" rotation="-0.00991589, 0.0102464, -0.134089, 0.990867" scale="1.0, 1.0, 1.0"/>
    <transform name="Bip01 L Finger0" translation="12.825, -0.714871, -4.0374" rotation="0.0549958, -0.0169116, 0.290762, 0.955064" scale="1.0, 1.0, 1.0"/>
    <transform name="Bip01 L Finger0Nub" translation="9.28433, 4.63631e-007, 4.10871e-007" rotation="0.0, 0.0, 0.0, 1.0" scale="1.0, 1.0, 1.0"/>
    <transform name="Bip01 R Clavicle" translation="-8.75081, 1.36474, -32.4073" rotation="-0.504218, -0.444216, 0.618187, 0.407776" scale="1.0, 1.0, 1.0"/>
    <transform name="Bip01 R UpperArm" translation="33.0219, 0.0, -1.21997e-006" rotation="0.619173, -0.157691, 0.0514303, 0.767537" scale="1.0, 1.0, 1.0"/>
    <transform name="Bip01 R Forearm" translation="22.361, -1.00995e-006, 0.0" rotation="0.0, 0.0, -0.464478, 0.885585" scale="1.0, 1.0, 1.0"/>
    <transform name="Bip01 R Hand" translation="31.134, 1.68554e-006, -3.68816e-006" rotation="0.00405059, -0.00193253, 0.0610095, 0.998127" scale="1.0, 1.0, 1.0"/>
    <transform name="Bip01 R Finger0" translation="12.825, -0.714871, 4.0374" rotation="0.0451384, 0.00623257, 0.165658, 0.98513" scale="1.0, 1.0, 1.0"/>
    <transform name="Bip01 R Finger0Nub" translation="9.28433, 0.0, -1.06828e-006" rotation="0.0, 0.0, 1.0, 0.0" scale="1.0, 1.0, 1.0"/>
    <transform name="Bip01 L Thigh" translation="-23.0781, 5.92853, 18.9418" rotation="0.762363, 0.645846, 0.000256994, 0.0410547" scale="1.0, 1.0, 1.0"/>
    <transform name="Bip01 L Calf" translation="44.7054, 2.71552e-006, 1.48188e-006" rotation="0.0, 0.0, -0.63924, 0.769007" scale="1.0, 1.0, 1.0"/>
    <transform name="Bip01 L HorseLink" translation="25.1575, 1.22784e-006, -1.82401e-006" rotation="0.0, 0.0, 0.831768, 0.555123" scale="1.0, 1.0, 1.0"/>
    <transform name="Bip01 L Foot" translation="19.0106, -1.43419e-006, 1.18817e-006" rotation="0.0125683, 0.0275599, -0.632197, 0.774215" scale="1.0, 1.0, 1.0"/>
    <transform name="Bip01 L Toe0" translation="7.55724, 12.3023, -7.38859e-007" rotation="0.0, 0.0, 0.707107, 0.707107" scale="1.0, 1.0, 1.0"/>
    <transform name="Bip01 L Toe0Nub" translation="1.13738, -1.37318e-006, 3.845e-007" rotation="0.0, 0.0, 1.0, 0.0" scale="1.0, 1.0, 1.0"/>
    <transform name="Bip01 R Thigh" translation="-23.3827, 5.82581, -20.1801" rotation="0.86664, 0.498925, 0.00234305, 0.00191236" scale="1.0, 1.0, 1.0"/>
    <transform name="Bip01 R Calf" translation="44.7054, -2.02173e-006, 6.60441e-007" rotation="0.0, 0.0, -0.491677, 0.870777" scale="1.0, 1.0, 1.0"/>
    <transform name="Bip01 R HorseLink" translation="25.1575, 4.19632e-006, 6.6248e-007" rotation="0.0, 0.0, 0.674262, 0.738492" scale="1.0, 1.0, 1.0"/>
    <transform name="Bip01 R Foot" translation="19.0106, 1.69399e-006, 6.07242e-007" rotation="-0.00120583, 0.0130575, -0.42407, 0.905534" scale="1.0, 1.0, 1.0"/>
    <transform name="Bip01 R Toe0" translation="7.55725, 12.3023, 9.36069e-007" rotation="0.0, 0.0, 0.707107, 0.707107" scale="1.0, 1.0, 1.0"/>
    <transform name="Bip01 R Toe0Nub" translation="1.13738, 0.0, 1.26628e-006" rotation="0.0, 0.0, 0.0, 1.0" scale="1.0, 1.0, 1.0"/>
    <transform name="Bip01 Tail" translation="-43.8143, 3.73519, -1.10413" rotation="-0.0542534, 0.0412887, 0.892996, 0.444872" scale="1.0, 1.0, 1.0"/>
    <transform name="Bip01 Tail1" translation="12.2215, -0.00961247, -1.15209e-005" rotation="-0.00469897, -0.0678315, -0.0768921, 0.994718" scale="1.0, 1.0, 1.0"/>
    <transform name="Bip01 Tail2" translation="12.2252, -0.0110541, 0.000718353" rotation="-0.02758, -0.0442582, 0.100047, 0.993615" scale="1.0, 1.0, 1.0"/>
    <transform name="Bip01 Tail3" translation="14.1817, -0.0111348, -0.000369342" rotation="0.00767676, 0.0631489, 0.133506, 0.989004" scale="1.0, 1.0, 1.0"/>
    <transform name="Bip01 TailNub" translation="14.4946, 3.50706e-006, 4.36984e-007" rotation="0.707388, 0.706825, 9.78562e-007, -9.81019e-007" scale="1.0, 1.0, 1.0"/>
    <transform name="Bip02" translation="0.696283, 26.1871, 161.07" rotation="0.239258, 0.239259, -0.665398, 0.665399" scale="1.0, 1.0, 1.0"/>
    <transform name="Bip02 Footsteps" translation="25.6836, -4.5893e-006, -31.0967" rotation="-0.239258, -0.239259, 0.665398, 0.665399" scale="1.0, 1.0, 1.0"/>
    <transform name="Bip02 Pelvis" translation="-1.15582, 0.0, 2.75735e-007" rotation="-0.499999, -0.5, -0.5, 0.500001" scale="1.0, 1.0, 1.0"/>
    <transform name="Bip02 Spine" translation="9.85905, -0.00650645, -0.00017725" rotation="0.0142334, -0.00195359, 0.191103, 0.981465" scale="1.0, 1.0, 1.0"/>
    <transform name="Bip02 Spine1" translation="8.81436, -0.00858899, -0.000249358" rotation="0.0143187, 0.000879268, -0.117075, 0.993019" scale="1.0, 1.0, 1.0"/>
    <transform name="Bip02 Spine2" translation="11.0981, -0.0105033, -0.000283667" rotation="0.0136579, 0.00471266, -0.182649, 0.983072" scale="1.0, 1.0, 1.0"/>
    <transform name="Bip02 Neck" translation="14.1475, -0.00517374, -5.52887e-007" rotation="0.0, 2.87955e-007, -0.103568, 0.994622" scale="1.0, 1.0, 1.0"/>
    <transform name="Bip02 Head" translation="6.64598, 2.18843e-006, -5.35042e-007" rotation="-0.0358065, -0.023502, 0.0719024, 0.996492" scale="1.0, 1.0, 1.0"/>
    <transform name="Bip02 HeadNub" translation="36.1861, -1.87754e-006, 0.0" rotation="0.0, 0.0, 0.0, 1.0" scale="1.0, 1.0, 1.0"/>
    <transform name="Bip02 Ponytail1" translation="20.4799, -7.48702, -11.0861" rotation="-0.0159542, -0.165446, 0.871323, -0.461702" scale="1.0, 1.0, 1.0"/>
    <transform name="Bip02 Ponytail11" translation="13.6611, -0.0105178, 0.000188118" rotation="-0.0182888, -0.0548492, -0.175024, 0.982865" scale="1.0, 1.0, 1.0"/>
    <transform name="Bip02 Ponytail12" translation="14.0709, -0.00891159, 0.000455588" rotation="-0.0202782, -0.0495916, 0.0952377, 0.994012" scale="1.0, 1.0, 1.0"/>
    <transform name="Bip02 Ponytail13" translation="11.4351, -0.0133706, 0.00124247" rotation="-0.024359, -0.0462175, 0.311851, 0.948694" scale="1.0, 1.0, 1.0"/>
    <transform name="Bip02 Ponytail1Nub" translation="20.8677, 5.24522e-006, 5.11481e-006" rotation="0.707388, 0.706825, 9.74129e-007, -9.82302e-007" scale="1.0, 1.0, 1.0"/>
    <transform name="Bip02 Ponytail2" translation="21.3887, -5.36787, 12.0409" rotation="-0.0534902, 0.142788, 0.877796, -0.45412" scale="1.0, 1.0, 1.0"/>
    <transform name="Bip02 Ponytail21" translation="14.6316, -0.0120759, -0.00129326" rotation="0.0645165, 0.0819412, -0.157636, 0.981975" scale="1.0, 1.0, 1.0"/>
    <transform name="Bip02 Ponytail22" translation="16.1045, -0.0119122, -0.00207534" rotation="0.0764533, 0.0217777, 0.205623, 0.975397" scale="1.0, 1.0, 1.0"/>
    <transform name="Bip02 Ponytail23" translation="16.5425, -0.0118031, -0.00225084" rotation="0.0896305, 0.000373246, 0.166867, 0.981897" scale="1.0, 1.0, 1.0"/>
    <transform name="Bip02 Ponytail2Nub" translation="15.9972, -7.51881e-006, -1.98715e-006" rotation="0.707388, 0.706825, 9.79113e-007, -9.81245e-007" scale="1.0, 1.0, 1.0"/>
    <transform name="Bip02 L Clavicle" translation="2.42821e-006, 0.00528373, 3.4594" rotation="0.4525, 0.00716773, 0.88469, -0.111876" scale="1.0, 1.0, 1.0"/>
    <transform name="Bip02 L UpperArm" translation="14.6244, -3.0207e-006, -7.49397e-006" rotation="0.0542128, 0.185067, -0.475921, 0.858085" scale="1.0, 1.0, 1.0"/>
    <transform name="Bip02 L Forearm" translation="27.0198, 2.35933e-006, -1.76015e-006" rotation="0.0, 0.0, -0.506612, 0.862174" scale="1.0, 1.0, 1.0"/>
    <transform name="Bip02 L Hand" translation="18.529, -1.04329e-005, 6.93142e-006" rotation="-0.706703, -0.0418215, 0.00340354, 0.706265" scale="1.0, 1.0, 1.0"/>
    <transform name="Bip02 L Finger0" translation="5.43344, -0.00308323, -6.3906" rotation="0.72447, 0.49349, -0.0213604, 0.480785" scale="1.0, 1.0, 1.0"/>
    <transform name="Bip02 L Finger01" translation="4.86918, -4.70219e-006, -2.6676e-006" rotation="0.0, 0.0, 0.32144, 0.94693" scale="1.0, 1.0, 1.0"/>
    <transform name="Bip02 L Finger0Nub" translation="5.85087, 3.25492e-006, 6.35964e-006" rotation="0.0, 0.0, 0.0, 1.0" scale="1.0, 1.0, 1.0"/>
    <transform name="Bip02 L Finger1" translation="12.6299, -1.21083, -4.22834" rotation="0.0261416, 0.0551698, 0.433243, 0.899207" scale="1.0, 1.0, 1.0"/>
    <transform name="Bip02 L Finger11" translation="4.71212, -6.79046e-006, -2.60955e-006" rotation="0.0, 0.0, 0.378649, 0.925541" scale="1.0, 1.0, 1.0"/>
    <transform name="Bip02 L Finger1Nub" translation="5.46606, -1.44452e-007, 2.57179e-006" rotation="0.0, 0.0, 0.0, 1.0" scale="1.0, 1.0, 1.0"/>
    <transform name="Bip02 L Finger2" translation="13.5902, 0.516083, 2.76275" rotation="-0.161872, -0.00151772, 0.328619, 0.930486" scale="1.0, 1.0, 1.0"/>
    <transform name="Bip02 L Finger21" translation="4.71931, 9.74877e-007, -9.10038e-006" rotation="0.0, 0.0, 0.378649, 0.925541" scale="1.0, 1.0, 1.0"/>
    <transform name="Bip02 L Finger2Nub" translation="5.89014, -1.07545e-006, 1.09743e-005" rotation="0.0, 0.0, 0.0, 1.0" scale="1.0, 1.0, 1.0"/>
    <transform name="Bip02 R Clavicle" translation="5.53877e-006, 0.00530223, -3.4594" rotation="-0.465653, -0.240417, 0.851382, 0.0226994" scale="1.0, 1.0, 1.0"/>
    <transform name="Bip02 R UpperArm" translation="14.6244, 6.03731e-007, -6.95422e-007" rotation="0.0802525, -0.0116431, -0.256183, 0.963221" scale="1.0, 1.0, 1.0"/>
    <transform name="Bip02 R Forearm" translation="27.0197, 1.00291e-006, -6.0992e-006" rotation="0.0, 0.0, -0.4412, 0.897409" scale="1.0, 1.0, 1.0"/>
    <transform name="Bip02 R Hand" translation="18.529, -4.14742e-006, -1.05782e-005" rotation="0.749205, 0.0338895, -0.057939, 0.658928" scale="1.0, 1.0, 1.0"/>
    <transform name="Bip02 R Finger0" translation="5.43343, -0.00308702, 6.39061" rotation="-0.740991, -0.260201, -0.118806, 0.607547" scale="1.0, 1.0, 1.0"/>
    <transform name="Bip02 R Finger01" translation="4.86918, -1.70084e-006, 1.60074e-006" rotation="0.0, 0.0, 0.241922, 0.970296" scale="1.0, 1.0, 1.0"/>
    <transform name="Bip02 R Finger0Nub" translation="5.85088, 3.38464e-006, -3.43894e-006" rotation="0.0, 0.0, 1.0, 0.0" scale="1.0, 1.0, 1.0"/>
    <transform name="Bip02 R Finger1" translation="12.6299, -1.21083, 4.22834" rotation="-0.026329, -0.0550806, 0.436297, 0.897729" scale="1.0, 1.0, 1.0"/>
    <transform name="Bip02 R Finger11" translation="4.71211, 6.02306e-006, 4.75935e-006" rotation="0.0, 0.0, 0.300706, 0.953717" scale="1.0, 1.0, 1.0"/>
    <transform name="Bip02 R Finger1Nub" translation="5.46605, -2.87301e-006, -7.60531e-007" rotation="0.0, 0.0, 1.0, 0.0" scale="1.0, 1.0, 1.0"/>
    <transform name="Bip02 R Finger2" translation="13.5902, 0.51608, -2.76275" rotation="0.0872453, 0.119637, 0.460566, 0.875188" scale="1.0, 1.0, 1.0"/>
    <transform name="Bip02 R Finger21" translation="4.71932, 9.89458e-007, -1.6275e-006" rotation="0.0, 0.0, 0.300706, 0.953717" scale="1.0, 1.0, 1.0"/>
    <transform name="Bip02 R Finger2Nub" translation="5.89014, -1.94126e-006, -1.2896e-006" rotation="0.0, 0.0, 1.0, 0.0" scale="1.0, 1.0, 1.0"/>
    <transform name="Bip02 L Thigh" translation="-9.05179, 3.95307, 9.10464" rotation="0.858016, 0.432862, 0.0521246, -0.27152" scale="1.0, 1.0, 1.0"/>
    <transform name="Bip02 L Calf" translation="27.795, -1.45534e-006, -3.94053e-006" rotation="0.0, 0.0, -0.740897, 0.671618" scale="1.0, 1.0, 1.0"/>
    <transform name="Bip02 L Foot" translation="29.6015, -2.76692e-006, -5.74945e-006" rotation="-0.0853664, -0.145868, 0.109389, 0.979525" scale="1.0, 1.0, 1.0"/>
    <transform name="Bip02 L Toe0" translation="14.534, 17.5771, 5.75923e-007" rotation="0.0, 0.0, 0.707107, 0.707107" scale="1.0, 1.0, 1.0"/>
    <transform name="Bip02 L Toe0Nub" translation="11.101, 3.55295e-006, -2.61605e-006" rotation="0.0, 0.0, 1.0, 0.0" scale="1.0, 1.0, 1.0"/>
    <transform name="Bip02 R Thigh" translation="-9.22103, 3.45681, -9.13631" rotation="0.850005, 0.413996, -0.181246, 0.270643" scale="1.0, 1.0, 1.0"/>
    <transform name="Bip02 R Calf" translation="27.795, 2.5924e-007, 2.91657e-006" rotation="0.0, 0.0, -0.777386, 0.629024" scale="1.0, 1.0, 1.0"/>
    <transform name="Bip02 R Foot" translation="29.6015, -2.04332e-006, 1.2499e-006" rotation="-0.0942646, 0.0156282, 0.263938, 0.959795" scale="1.0, 1.0, 1.0"/>
    <transform name="Bip02 R Toe0" translation="14.534, 17.5771, 3.17958e-006" rotation="0.0, 0.0, 0.707107, 0.707107" scale="1.0, 1.0, 1.0"/>
    <transform name="Bip02 R Toe0Nub" translation="11.101, 1.13876e-006, 2.77505e-006" rotation="0.0, 0.0, 0.0, 1.0" scale="1.0, 1.0, 1.0"/>
    <transform name="Bip02 Tail" translation="-7.96064, -6.39012, 0.243635" rotation="0.0315584, 0.158367, 0.979812, 0.117868" scale="1.0, 1.0, 1.0"/>
    <transform name="Bip02 Tail1" translation="18.4115, -0.0137153, 9.28813e-005" rotation="-0.00323772, 0.00559762, -0.0417851, 0.999106" scale="1.0, 1.0, 1.0"/>
    <transform name="Bip02 Tail2" translation="17.2738, -0.0145931, -0.00186346" rotation="0.0707023, 0.0557405, -0.181504, 0.97926" scale="1.0, 1.0, 1.0"/>
    <transform name="Bip02 TailNub" translation="19.829, -1.77779e-006, 0.0" rotation="0.707388, 0.706825, 9.76779e-007, -9.68684e-007" scale="1.0, 1.0, 1.0"/>
    <transform name="Bone01" translation="-1.02917, 10.6656, 0.0733636" rotation="0.634016, 0.425062, 0.273252, 0.585388" scale="1.0, 1.0, 1.0"/>
    <transform name="Bone02" translation="23.0916, 4.08364e-006, 0.0" rotation="0.0, 0.0, 0.0, 1.0" scale="1.0, 1.0, 1.0"/>
    <transform name="rider" translation="174.459, 3.32103, -13.7466" rotation="0.0, 0.0, 0.0, 1.0" scale="1.0, 1.0, 1.0"/>
  </frame>

  <frame>
    <transform name="bison" translation="-529.682, 341.794, -38.2763" rotation="0.0, 9.28547e-007, 0.0, 1.0" scale="35.5709, 28.4567, 28.4567"/>
    <transform name="Omni03" translation="-1642.78, -3829.81, -4202.06" rotation="0.0, 0.0, 0.0, 1.0" scale="34.5, 34.5, 34.5"/>
    <transform name="Omni05" translation="-3561.19, 3757.06, -2462.9" rotation="0.0, 0.0, 0.0, 1.0" scale="34.5, 34.5, 34.5"/>
    <transform name="Omni06" translation="4739.17, 2891.95, 11806.9" rotation="0.0, 0.0, 0.0, 1.0" scale="34.5, 34.5, 34.5"/>
    <transform name="Omni07" translation="13411.8, 5143.02, -2619.83" rotation="0.0, 0.0, 0.0, 1.0" scale="34.5, 34.5, 34.5"/>
    <transform name="Omni08" translation="-18659.1, 6889.32, 1469.94" rotation="0.0, 0.0, 0.0, 1.0" scale="34.5, 34.5, 34.5"/>
    <transform name="Omni09" translation="2752.18, -15860.6, 10088.9" rotation="0.0, 0.0, 0.0, 1.0" scale="34.5, 34.5, 34.5"/>
    <transform name="Bip01" translation="-0.165566, 88.3778, 71.7309" rotation="0.43777, 0.437761, -0.555299, 0.555307" scale="1.0, 1.0, 1.0"/>
    <transform name="Bip01 Footsteps" translation="70.2872, -0.00123507, -16.8745" rotation="-0.43777, -0.437761, 0.555299, 0.555307" scale="1.0, 1.0, 1.0"/>
    <transform name="Bip01 Pelvis" translation="0.00652377, -0.250966, 5.44913e-006" rotation="-0.49699, -0.496991, -0.502991, 0.502992" scale="1.0, 1.0, 1.0"/>
    <transform name="Bip01 Spine" translation="23.9187, -1.44513, 0.287022" rotation="0.00136858, -0.0096675, -0.0197026, 0.999758" scale="1.0, 1.0, 1.0"/>
    <transform name="Bip01 Spine1" translation="35.5272, -0.0281958, 2.2423e-005" rotation="-0.000451975, 0.00131155, 0.0403035, 0.999187" scale="1.0, 1.0, 1.0"/>
    <transform name="Bip01 Spine2" translation="35.5284, -0.026387, -6.00646e-005" rotation="0.000925633, 0.00317387, 0.0645205, 0.997911" scale="1.0, 1.0, 1.0"/>
    <transform name="Bip01 Neck" translation="33.4172, -0.0106915, 0.0" rotation="2.77368e-007, -5.41371e-006, -0.0152775, 0.999883" scale="1.0, 1.0, 1.0"/>
    <transform name="Bip01 Neck1" translation="13.4424, -0.0106941, 0.0" rotation="-6.65119e-006, 5.37008e-005, 0.031086, 0.999517" scale="1.0, 1.0, 1.0"/>
    <transform name="Bip01 Head" translation="13.4417, 1.83921e-006, 0.0" rotation="-0.00628936, -0.00122017, -0.249398, 0.96838" scale="1.0, 1.0, 1.0"/>
    <transform name="Bip01 HeadNub" translation="41.8745, 5.21999e-006, 0.0" rotation="0.0, 0.0, 0.0, 1.0" scale="1.0, 1.0, 1.0"/>
    <transform name="Bip01 Ponytail1" translation="1.85163, 47.5243, 9.39732e-005" rotation="0.0308782, -0.0231123, 0.762745, 0.645548" scale="1.0, 1.0, 1.0"/>
    <transform name="Bip01 Ponytail11" translation="12.6802, -0.00988007, -4.68331e-005" rotation="0.00630915, -0.0380494, 0.104179, 0.99381" scale="1.0, 1.0, 1.0"/>
    <transform name="Bip01 Ponytail1Nub" translation="12.6781, -2.19629e-006, 2.52396e-007" rotation="0.707388, 0.706825, 9.79634e-007, -9.81097e-007" scale="1.0, 1.0, 1.0"/>
    <transform name="Bip01 L Clavicle" translation="-8.82628, -0.691617, 32.4075" rotation="0.417866, 0.528951, 0.661211, 0.329239" scale="1.0, 1.0, 1.0"/>
    <transform name="Bip01 L UpperArm" translation="33.0219, 9.17199e-007, 1.49018e-006" rotation="-0.662557, -0.198063, -0.385385, 0.610957" scale="1.0, 1.0, 1.0"/>
    <transform name="Bip01 L Forearm" translation="22.361, 5.8799e-007, -7.22313e-007" rotation="0.0, 0.0, -0.000772109, 1.0" scale="1.0, 1.0, 1.0"/>
    <transform name="Bip01 L Hand" translation="31.134, 6.61988e-007, 1.46452e-007" rotation="-0.0169507, 0.00629753, -0.0443891, 0.998851" scale="1.0, 1.0, 1.0"/>
    <transform name="Bip01 L Finger0" translation="12.825, -0.714869, -4.0374" rotation="0.0515408, -0.00768919, 0.106053, 0.992994" scale="1.0, 1.0, 1.0"/>
    <transform name="Bip01 L Finger0Nub" translation="9.28433, -2.45334e-006, 9.35897e-007" rotation="0.0, 0.0, 0.0, 1.0" scale="1.0, 1.0, 1.0"/>
    <transform name="Bip01 R Clavicle" translation="-8.82698, -0.691487, -32.4073" rotation="-0.500058, -0.462707, 0.640999, 0.353503" scale="1.0, 1.0, 1.0"/>
    <transform name="Bip01 R UpperArm" translation="33.0219, -1.30546e-006, -3.45903e-006" rotation="0.645245, -0.0787759, -0.0845666, 0.755183" scale="1.0, 1.0, 1.0"/>
    <transform name="Bip01 R Forearm" translation="22.361, 2.28357e-007, 6.4524e-007" rotation="0.0, 0.0, -0.387915, 0.921695" scale="1.0, 1.0, 1.0"/>
    <transform name="Bip01 R Hand" translation="31.134, 1.67686e-006, 1.93295e-006" rotation="0.0114373, 0.00282563, 0.0313578, 0.999439" scale="1.0, 1.0, 1.0"/>
    <transform name="Bip01 R Finger0" translation="12.825, -0.714871, 4.0374" rotation="0.0460492, 0.00375791, 0.154262, 0.986949" scale="1.0, 1.0, 1.0"/>
    <transform name="Bip01 R Finger0Nub" translation="9.28433, -1.97626e-007, -4.62927e-007" rotation="0.0, 0.0, 1.0, 0.0" scale="1.0, 1.0, 1.0"/>
    <transform name="Bip01 L Thigh" translation="-23.5811, 0.562443, 19.7312" rotation="0.809471, 0.586557, -0.00774479, 0.0254584" scale="1.0, 1.0, 1.0"/>
    <transform name="Bip01 L Calf" translation="44.7054, -2.39594e-006, -7.1643e-007" rotation="0.0, 0.0, -0.679845, 0.733356" scale="1.0, 1.0, 1.0"/>
    <transform name="Bip01 L HorseLink" translation="25.1575, 0.0, -1.77211e-007" rotation="0.0, 0.0, 0.844222, 0.535993" scale="1.0, 1.0, 1.0"/>
    <transform name="Bip01 L Foot" translation="19.0106, 1.14874e-006, 6.38287e-007" rotation="0.0200602, 0.0167477, -0.33446, 0.942048" scale="1.0, 1.0, 1.0"/>
    <transform name="Bip01 L Toe0" translation="7.55724, 12.3023, 4.51616e-007" rotation="0.0, 0.0, 0.707107, 0.707107" scale="1.0, 1.0, 1.0"/>
    <transform name="Bip01 L Toe0Nub" translation="1.13738, 0.0, -9.2355e-007" rotation="0.0, 0.0, 1.0, 0.0" scale="1.0, 1.0, 1.0"/>
    <transform name="Bip01 R Thigh" translation="-24.3352, 0.440431, -19.3846" rotation="0.873056, 0.487456, -0.0111096, -0.00595092" scale="1.0, 1.0, 1.0"/>
    <transform name="Bip01 R Calf" translation="44.7054, 2.65051e-006, 1.20451e-006" rotation="0.0, 0.0, -0.590977, 0.806688" scale="1.0, 1.0, 1.0"/>
    <transform name="Bip01 R HorseLink" translation="25.1575, 4.49202e-006, -1.26836e-006" rotation="0.0, 0.0, 0.679983, 0.733228" scale="1.0, 1.0, 1.0"/>
    <transform name="Bip01 R Foot" translation="19.0106, -1.7504e-006, 7.461e-007" rotation="-0.00196359, 0.0111233, -0.423412, 0.905867" scale="1.0, 1.0, 1.0"/>
    <transform name="Bip01 R Toe0" translation="7.55724, 12.3023, 0.0" rotation="0.0, 0.0, 0.707107, 0.707107" scale="1.0, 1.0, 1.0"/>
    <transform name="Bip01 R Toe0Nub" translation="1.13738, 4.82881e-007, -1.0986e-006" rotation="0.0, 0.0, 0.0, 1.0" scale="1.0, 1.0, 1.0"/>
    <transform name="Bip01 Tail" translation="-43.535, -6.22025, 0.333815" rotation="-0.0581547, 0.0368968, 0.817029, 0.572469" scale="1.0, 1.0, 1.0"/>
    <transform name="Bip01 Tail1" translation="12.22, -0.00924272, -6.66131e-005" rotation="-0.00737582, -0.0676226, -0.158282, 0.985048" scale="1.0, 1.0, 1.0"/>
    <transform name="Bip01 Tail2" translation="12.229, -0.00947731, 0.00159225" rotation="-0.0533617, -0.0699026, 0.279579, 0.956087" scale="1.0, 1.0, 1.0"/>
    <transform name="Bip01 Tail3" translation="14.1845, -0.00993934, -0.000465748" rotation="0.0111079, 0.0360684, 0.263285, 0.96398" scale="1.0, 1.0, 1.0"/>
    <transform name="Bip01 TailNub" translation="14.4946, 8.11589e-007, 8.8002e-007" rotation="0.707388, 0.706825, 9.82135e-007, -9.82051e-007" scale="1.0, 1.0, 1.0"/>
    <transform name="Bip02" translation="0.696283, 26.1395, 162.939" rotation="0.130074, 0.130074, -0.69504, 0.695041" scale="1.0, 1.0, 1.0"/>
    <transform name="Bip02 Footsteps" translation="16.9072, -4.95836e-006, -43.5891" rotation="-0.130074, -0.130074, 0.69504, 0.695041" scale="1.0, 1.0, 1.0"/>
    <transform name="Bip02 Pelvis" translation="-1.15582, 0.0, -3.87434e-007" rotation="-0.499999, -0.5, -0.5, 0.500001" scale="1.0, 1.0, 1.0"/>
    <transform name="Bip02 Spine" translation="9.85801, -0.00681802, -0.000342846" rotation="0.025721, -0.00135626, 0.115382, 0.992987" scale="1.0, 1.0, 1.0"/>
    <transform name="Bip02 Spine1" translation="8.81448, -0.00860916, -0.000448017" rotation="0.0256074, 0.00111335, -0.109187, 0.993691" scale="1.0, 1.0, 1.0"/>
    <transform name="Bip02 Spine2" translation="11.095, -0.00869849, -0.000446939" rotation="0.0241578, 0.00856803, -0.336626, 0.94129" scale="1.0, 1.0, 1.0"/>
    <transform name="Bip02 Neck" translation="14.1478, -0.00522489, 0.0" rotation="0.0, 2.17571e-007, -0.0790484, 0.996871" scale="1.0, 1.0, 1.0"/>
    <transform name="Bip02 Head" translation="6.64599, 2.95291e-006, -1.713e-007" rotation="-0.0665713, -0.0382859, 0.379291, 0.922085" scale="1.0, 1.0, 1.0"/>
    <transform name="Bip02 HeadNub" translation="36.1861, 1.63579e-006, 0.0" rotation="0.0, 0.0, 0.0, 1.0" scale="1.0, 1.0, 1.0"/>
    <transform name="Bip02 Ponytail1" translation="20.4818, -7.48489, -11.0858" rotation="-0.00857057, -0.168732, 0.926015, -0.337569" scale="1.0, 1.0, 1.0"/>
    <transform name="Bip02 Ponytail11" translation="13.6593, -0.00967157, 0.000156068" rotation="-0.0187729, -0.0417744, -0.262135, 0.963944" scale="1.0, 1.0, 1.0"/>
    <transform name="Bip02 Ponytail12" translation="14.0685, -0.00906028, 0.000363265" rotation="-0.0210608, -0.0354014, -0.0357308, 0.998512" scale="1.0, 1.0, 1.0"/>
    <transform name="Bip02 Ponytail13" translation="11.4352, -0.0132903, 0.00121044" rotation="-0.029741, -0.0259394, 0.315342, 0.948157" scale="1.0, 1.0, 1.0"/>
    <transform name="Bip02 Ponytail1Nub" translation="20.8677, 3.15628e-006, -4.2029e-006" rotation="0.707388, 0.706825, 9.78772e-007, -9.80119e-007" scale="1.0, 1.0, 1.0"/>
    <transform name="Bip02 Ponytail2" translation="21.3936, -5.36375, 12.0415" rotation="-0.0617197, 0.114973, 0.972665, -0.192082" scale="1.0, 1.0, 1.0"/>
    <transform name="Bip02 Ponytail21" translation="14.6335, -0.012582, -0.00117369" rotation="0.0506801, 0.0543008, -0.0822179, 0.993843" scale="1.0, 1.0, 1.0"/>
    <transform name="Bip02 Ponytail22" translation="16.1032, -0.0125536, -0.000727647" rotation="0.0371236, -0.0622491, 0.148281, 0.986286" scale="1.0, 1.0, 1.0"/>
    <transform name="Bip02 Ponytail23" translation="16.5425, -0.0120191, -0.0009329" rotation="0.0540391, -0.101745, 0.160205, 0.980338" scale="1.0, 1.0, 1.0"/>
    <transform name="Bip02 Ponytail2Nub" translation="15.9972, 2.20679e-006, -2.71972e-006" rotation="0.707388, 0.706825, 9.80493e-007, -9.79596e-007" scale="1.0, 1.0, 1.0"/>
    <transform name="Bip02 L Clavicle" translation="9.85105e-006, 0.0052876, 3.4594" rotation="0.362466, 0.139076, 0.921137, -0.0279917" scale="1.0, 1.0, 1.0"/>
    <transform name="Bip02 L UpperArm" translation="14.6244, 0.0, -2.15635e-006" rotation="0.119347, 0.288443, -0.184242, 0.931993" scale="1.0, 1.0, 1.0"/>
    <transform name="Bip02 L Forearm" translation="27.0197, -3.80157e-006, -2.69762e-007" rotation="0.0, 0.0, -0.310286, 0.950643" scale="1.0, 1.0, 1.0"/>
    <transform name="Bip02 L Hand" translation="18.529, 8.43279e-006, -3.29918e-006" rotation="-0.706721, -0.041171, 0.00294559, 0.706287" scale="1.0, 1.0, 1.0"/>
    <transform name="Bip02 L Finger0" translation="5.43344, -0.00308351, -6.39061" rotation="0.714389, 0.466923, -0.0891483, 0.513502" scale="1.0, 1.0, 1.0"/>
    <transform name="Bip02 L Finger01" translation="4.86918, 1.52066e-006, -2.38982e-006" rotation="0.0, 0.0, 0.32144, 0.94693" scale="1.0, 1.0, 1.0"/>
    <transform name="Bip02 L Finger0Nub" translation="5.85088, 2.11356e-006, -3.13303e-006" rotation="0.0, 0.0, 0.0, 1.0" scale="1.0, 1.0, 1.0"/>
    <transform name="Bip02 L Finger1" translation="12.6299, -1.21083, -4.22834" rotation="0.0227714, 0.056644, 0.378299, 0.923668" scale="1.0, 1.0, 1.0"/>
    <transform name="Bip02 L Finger11" translation="4.71212, -1.31523e-006, 6.00194e-006" rotation="0.0, 0.0, 0.378649, 0.925541" scale="1.0, 1.0, 1.0"/>
    <transform name="Bip02 L Finger1Nub" translation="5.46605, 1.56416e-006, 2.259e-007" rotation="0.0, 0.0, 0.0, 1.0" scale="1.0, 1.0, 1.0"/>
    <transform name="Bip02 L Finger2" translation="13.5902, 0.516084, 2.76275" rotation="-0.161791, -0.00533961, 0.306556, 0.937986" scale="1.0, 1.0, 1.0"/>
    <transform name="Bip02 L Finger21" translation="4.71931, 1.31692e-006, -5.90844e-006" rotation="0.0, 0.0, 0.378649, 0.925541" scale="1.0, 1.0, 1.0"/>
    <transform name="Bip02 L Finger2Nub" translation="5.89014, -1.29914e-006, 8.26256e-006" rotation="0.0, 0.0, 0.0, 1.0" scale="1.0, 1.0, 1.0"/>
    <transform name="Bip02 R Clavicle" translation="-1.09182e-006, 0.00530052, -3.4594" rotation="-0.427651, -0.306745, 0.846533, 0.0800282" scale="1.0, 1.0, 1.0"/>
    <transform name="Bip02 R UpperArm" translation="14.6244, 0.0, -1.36759e-005" rotation="-0.051609, -0.267862, -0.0427608, 0.961123" scale="1.0, 1.0, 1.0"/>
    <transform name="Bip02 R Forearm" translation="27.0197, -2.44865e-006, -4.29175e-007" rotation="0.0, 0.0, -0.233895, 0.972262" scale="1.0, 1.0, 1.0"/>
    <transform name="Bip02 R Hand" translation="18.529, 2.97336e-006, 0.0" rotation="0.692031, 0.0348104, -0.0357484, 0.720142" scale="1.0, 1.0, 1.0"/>
    <transform name="Bip02 R Finger0" translation="5.43344, -0.00307729, 6.3906" rotation="-0.735379, -0.275662, -0.131503, 0.604926" scale="1.0, 1.0, 1.0"/>
    <transform name="Bip02 R Finger01" translation="4.86918, 5.35638e-006, 9.86249e-006" rotation="0.0, 0.0, 0.241922, 0.970296" scale="1.0, 1.0, 1.0"/>
    <transform name="Bip02 R Finger0Nub" translation="5.85088, 1.89473e-006, -6.03224e-006" rotation="0.0, 0.0, 1.0, 0.0" scale="1.0, 1.0, 1.0"/>
    <transform name="Bip02 R Finger1" translation="12.6299, -1.21083, 4.22834" rotation="-0.0251697, -0.0556198, 0.417401, 0.906669" scale="1.0, 1.0, 1.0"/>
    <transform name="Bip02 R Finger11" translation="4.71211, 2.26645e-007, 7.86403e-006" rotation="0.0, 0.0, 0.300706, 0.953717" scale="1.0, 1.0, 1.0"/>
    <transform name="Bip02 R Finger1Nub" translation="5.46606, 1.18752e-006, -1.94269e-006" rotation="0.0, 0.0, 1.0, 0.0" scale="1.0, 1.0, 1.0"/>
    <transform name="Bip02 R Finger2" translation="13.5902, 0.516089, -2.76275" rotation="0.111958, 0.0780682, 0.436783, 0.889152" scale="1.0, 1.0, 1.0"/>
    <transform name="Bip02 R Finger21" translation="4.71931, 1.92075e-006, 6.4033e-006" rotation="0.0, 0.0, 0.300706, 0.953717" scale="1.0, 1.0, 1.0"/>
    <transform name="Bip02 R Finger2Nub" translation="5.89015, -1.62965e-006, -6.79642e-006" rotation="0.0, 0.0, 1.0, 0.0" scale="1.0, 1.0, 1.0"/>
    <transform name="Bip02 L Thigh" translation="-9.5152, 2.7295, 9.08016" rotation="0.747015, 0.622661, 0.0738059, -0.220938" scale="1.0, 1.0, 1.0"/>
    <transform name="Bip02 L Calf" translation="27.795, -2.34316e-006, 5.09977e-007" rotation="0.0, 0.0, -0.570871, 0.821039" scale="1.0, 1.0, 1.0"/>
    <transform name="Bip02 L Foot" translation="29.6015, 3.05122e-007, 4.79891e-006" rotation="-0.116499, -0.0783305, 0.240556, 0.96043" scale="1.0, 1.0, 1.0"/>
    <transform name="Bip02 L Toe0" translation="14.534, 17.5771, 6.14401e-007" rotation="0.0, 0.0, 0.707107, 0.707107" scale="1.0, 1.0, 1.0"/>
    <transform name="Bip02 L Toe0Nub" translation="11.101, 2.73749e-006, 2.60523e-007" rotation="0.0, 0.0, 1.0, 0.0" scale="1.0, 1.0, 1.0"/>
    <transform name="Bip02 R Thigh" translation="-9.67265, 1.80303, -9.1441" rotation="0.739182, 0.581381, -0.209717, 0.267629" scale="1.0, 1.0, 1.0"/>
    <transform name="Bip02 R Calf" translation="27.795, -4.02342e-006, -1.46045e-006" rotation="0.0, 0.0, -0.677079, 0.73591" scale="1.0, 1.0, 1.0"/>
    <transform name="Bip02 R Foot" translation="29.6015, 3.46086e-007, 1.25644e-006" rotation="-0.0966632, 0.0841367, 0.39316, 0.910496" scale="1.0, 1.0, 1.0"/>
    <transform name="Bip02 R Toe0" translation="14.534, 17.5771, -2.05643e-006" rotation="0.0, 0.0, 0.707107, 0.707107" scale="1.0, 1.0, 1.0"/>
    <transform name="Bip02 R Toe0Nub" translation="11.101, -6.13149e-007, 7.38387e-007" rotation="0.0, 0.0, 0.0, 1.0" scale="1.0, 1.0, 1.0"/>
    <transform name="Bip02 Tail" translation="-6.88856, -7.52292, 0.437942" rotation="-0.0152406, 0.177679, 0.981563, 0.0687867" scale="1.0, 1.0, 1.0"/>
    <transform name="Bip02 Tail1" translation="18.414, -0.0136941, 0.000164862" rotation="-0.00467276, -0.0271534, 0.0485577, 0.99844" scale="1.0, 1.0, 1.0"/>
    <transform name="Bip02 Tail2" translation="17.2786, -0.0156674, -0.0015638" rotation="0.0513759, 0.0612277, -0.0282859, 0.996399" scale="1.0, 1.0, 1.0"/>
    <transform name="Bip02 TailNub" translation="19.829, -2.8535e-006, 1.51508e-006" rotation="0.707388, 0.706825, 9.76419e-007, -9.76664e-007" scale="1.0, 1.0, 1.0"/>
    <transform name="Bone01" translation="-1.02917, 10.6656, 0.0733636" rotation="0.634016, 0.425062, 0.273252, 0.585388" scale="1.0, 1.0, 1.0"/>
    <transform name="Bone02" translation="23.0916, 4.51051e-006, -2.18929e-006" rotation="0.0, 0.0, 0.0, 1.0" scale="1.0, 1.0, 1.0"/>
    <transform name="rider" translation="174.459, 3.32103, -13.7466" rotation="0.0, 0.0, 0.0, 1.0" scale="1.0, 1.0, 1.0"/>
  </frame>

  <frame>
    <transform name="bison" translation="-529.682, 341.794, -38.2763" rotation="0.0, 9.28547e-007, 0.0, 1.0" scale="35.5709, 28.4567, 28.4567"/>
    <transform name="Omni03" translation="-1642.78, -3829.81, -4202.06" rotation="0.0, 0.0, 0.0, 1.0" scale="34.5, 34.5, 34.5"/>
    <transform name="Omni05" translation="-3561.19, 3757.06, -2462.9" rotation="0.0, 0.0, 0.0, 1.0" scale="34.5, 34.5, 34.5"/>
    <transform name="Omni06" translation="4739.17, 2891.95, 11806.9" rotation="0.0, 0.0, 0.0, 1.0" scale="34.5, 34.5, 34.5"/>
    <transform name="Omni07" translation="13411.8, 5143.02, -2619.83" rotation="0.0, 0.0, 0.0, 1.0" scale="34.5, 34.5, 34.5"/>
    <transform name="Omni08" translation="-18659.1, 6889.32, 1469.94" rotation="0.0, 0.0, 0.0, 1.0" scale="34.5, 34.5, 34.5"/>
    <transform name="Omni09" translation="2752.18, -15860.6, 10088.9" rotation="0.0, 0.0, 0.0, 1.0" scale="34.5, 34.5, 34.5"/>
    <transform name="Bip01" translation="-0.165566, 88.3778, 80.3536" rotation="0.465794, 0.465792, -0.532011, 0.532014" scale="1.0, 1.0, 1.0"/>
    <transform name="Bip01 Footsteps" translation="77.9232, -0.00038674, -10.3885" rotation="-0.465794, -0.465792, 0.532011, 0.532014" scale="1.0, 1.0, 1.0"/>
    <transform name="Bip01 Pelvis" translation="5.87809, -0.826999, -2.67743e-006" rotation="0.502787, 0.502787, 0.497197, -0.497198" scale="1.0, 1.0, 1.0"/>
    <transform name="Bip01 Spine" translation="23.914, -1.4445, -0.267479" rotation="0.000314914, -0.00606164, -0.107125, 0.994227" scale="1.0, 1.0, 1.0"/>
    <transform name="Bip01 Spine1" translation="35.53, -0.0278314, 2.2806e-005" rotation="-0.000701595, 0.00324845, 0.0899248, 0.995943" scale="1.0, 1.0, 1.0"/>
    <transform name="Bip01 Spine2" translation="35.5294, -0.026244, -7.53455e-005" rotation="0.000631074, 0.00952976, 0.082964, 0.996507" scale="1.0, 1.0, 1.0"/>
    <transform name="Bip01 Neck" translation="33.418, -0.010697, 0.0" rotation="1.4667e-007, -3.362e-006, 0.0228368, 0.999739" scale="1.0, 1.0, 1.0"/>
    <transform name="Bip01 Neck1" translation="13.4434, -0.0105637, 0.0" rotation="-4.32665e-006, 2.42893e-005, 0.0794293, 0.996841" scale="1.0, 1.0, 1.0"/>
    <transform name="Bip01 Head" translation="13.4417, -2.12937e-006, 0.0" rotation="-0.00525668, -0.000804706, -0.264147, 0.964468" scale="1.0, 1.0, 1.0"/>
    <transform name="Bip01 HeadNub" translation="41.8745, 2.79785e-006, 0.0" rotation="0.0, 0.0, 0.0, 1.0" scale="1.0, 1.0, 1.0"/>
    <transform name="Bip01 Ponytail1" translation="1.85135, 47.5255, 0.000133729" rotation="0.0413007, -0.0304022, 0.800433, 0.597224" scale="1.0, 1.0, 1.0"/>
    <transform name="Bip01 Ponytail11" translation="12.6814, -0.00954858, -7.10677e-006" rotation="0.008792, -0.0505239, 0.164823, 0.984989" scale="1.0, 1.0, 1.0"/>
    <transform name="Bip01 Ponytail1Nub" translation="12.6781, 1.65163e-006, 3.74711e-007" rotation="0.707388, 0.706825, 9.82814e-007, -9.77522e-007" scale="1.0, 1.0, 1.0"/>
    <transform name="Bip01 L Clavicle" translation="-8.85427, -0.0173473, 32.4075" rotation="0.556773, 0.435679, 0.53701, 0.460226" scale="1.0, 1.0, 1.0"/>
    <transform name="Bip01 L UpperArm" translation="33.0219, -1.60913e-006, 1.48907e-006" rotation="-0.669147, 0.321841, 0.182448, 0.644495" scale="1.0, 1.0, 1.0"/>
    <transform name="Bip01 L Forearm" translation="22.361, -1.77008e-006, 1.65463e-006" rotation="0.0, 0.0, -0.603423, 0.797421" scale="1.0, 1.0, 1.0"/>
    <transform name="Bip01 L Hand" translation="31.134, 1.32833e-006, -3.91009e-007" rotation="-0.0240073, 0.00233031, 0.047441, 0.998583" scale="1.0, 1.0, 1.0"/>
    <transform name="Bip01 L Finger0" translation="12.825, -0.714869, -4.0374" rotation="0.0452807, 0.00173807, -0.0759517, 0.996081" scale="1.0, 1.0, 1.0"/>
    <transform name="Bip01 L Finger0Nub" translation="9.28433, 2.44451e-006, 1.45617e-007" rotation="0.0, 0.0, 0.0, 1.0" scale="1.0, 1.0, 1.0"/>
    <transform name="Bip01 R Clavicle" translation="-8.85469, -0.0171832, -32.4074" rotation="0.64285, 0.345959, -0.518361, -0.445375" scale="1.0, 1.0, 1.0"/>
    <transform name="Bip01 R UpperArm" translation="33.0219, 2.73084e-006, -2.00392e-006" rotation="0.593759, -0.353774, 0.119235, 0.712795" scale="1.0, 1.0, 1.0"/>
    <transform name="Bip01 R Forearm" translation="22.361, 2.06344e-007, -7.39018e-007" rotation="0.0, 0.0, -0.506493, 0.862244" scale="1.0, 1.0, 1.0"/>
    <transform name="Bip01 R Hand" translation="31.134, 0.0, -1.36931e-006" rotation="0.0188863, 0.0075172, 0.00246855, 0.99979" scale="1.0, 1.0, 1.0"/>
    <transform name="Bip01 R Finger0" translation="12.825, -0.714872, 4.0374" rotation="0.0468049, 0.0013093, 0.14632, 0.988129" scale="1.0, 1.0, 1.0"/>
    <transform name="Bip01 R Finger0Nub" translation="9.28433, -1.17257e-006, 1.30036e-006" rotation="0.0, 0.0, 1.0, 0.0" scale="1.0, 1.0, 1.0"/>
    <transform name="Bip01 L Thigh" translation="-23.4334, -3.64437, 20.1185" rotation="0.783515, 0.621077, -0.0137608, 0.0133574" scale="1.0, 1.0, 1.0"/>
    <transform name="Bip01 L Calf" translation="44.7054, -2.32771e-007, 1.26567e-007" rotation="0.0, 0.0, -0.55781, 0.829969" scale="1.0, 1.0, 1.0"/>
    <transform name="Bip01 L HorseLink" translation="25.1575, 4.71246e-006, 1.10296e-006" rotation="0.0, 0.0, 0.769195, 0.639015" scale="1.0, 1.0, 1.0"/>
    <transform name="Bip01 L Foot" translation="19.0106, -6.49278e-007, -9.2632e-007" rotation="0.0123008, 0.0121566, -0.438952, 0.898344" scale="1.0, 1.0, 1.0"/>
    <transform name="Bip01 L Toe0" translation="7.55725, 12.3023, -7.84213e-007" rotation="0.0, 0.0, 0.707107, 0.707107" scale="1.0, 1.0, 1.0"/>
    <transform name="Bip01 L Toe0Nub" translation="1.13738, 3.35377e-007, 2.85309e-007" rotation="0.0, 0.0, 1.0, 0.0" scale="1.0, 1.0, 1.0"/>
    <transform name="Bip01 R Thigh" translation="-23.9023, -3.71972, -19.0019" rotation="0.74759, 0.663842, -0.0190264, -0.0077593" scale="1.0, 1.0, 1.0"/>
    <transform name="Bip01 R Calf" translation="44.7054, 1.42984e-006, -1.32563e-006" rotation="0.0, 0.0, -0.552239, 0.833686" scale="1.0, 1.0, 1.0"/>
    <transform name="Bip01 R HorseLink" translation="25.1575, 2.71376e-006, 1.27324e-006" rotation="0.0, 0.0, 0.753087, 0.657921" scale="1.0, 1.0, 1.0"/>
    <transform name="Bip01 R Foot" translation="19.0106, -1.65578e-006, -3.39065e-007" rotation="-0.00270783, 0.0119148, -0.422444, 0.906307" scale="1.0, 1.0, 1.0"/>
    <transform name="Bip01 R Toe0" translation="7.55724, 12.3023, -1.0744e-006" rotation="0.0, 0.0, 0.707107, 0.707107" scale="1.0, 1.0, 1.0"/>
    <transform name="Bip01 R Toe0Nub" translation="1.13738, 0.0, 0.0" rotation="0.0, 0.0, 0.0, 1.0" scale="1.0, 1.0, 1.0"/>
    <transform name="Bip01 Tail" translation="-41.7679, -13.714, 1.01634" rotation="-0.0595437, 0.0444964, 0.844703, 0.530049" scale="1.0, 1.0, 1.0"/>
    <transform name="Bip01 Tail1" translation="12.2185, -0.00863282, -0.000117061" rotation="-0.0102339, -0.0671352, -0.237379, 0.96904" scale="1.0, 1.0, 1.0"/>
    <transform name="Bip01 Tail2" translation="12.2288, -0.0094567, 0.00206582" rotation="-0.0655655, -0.104686, 0.277347, 0.952796" scale="1.0, 1.0, 1.0"/>
    <transform name="Bip01 Tail3" translation="14.1829, -0.0107424, -0.000186101" rotation="0.00640326, 0.0098788, 0.185427, 0.982588" scale="1.0, 1.0, 1.0"/>
    <transform name="Bip01 TailNub" translation="14.4946, -7.31935e-007, -1.41861e-006" rotation="0.707388, 0.706825, 9.79808e-007, -9.82745e-007" scale="1.0, 1.0, 1.0"/>
    <transform name="Bip02" translation="0.696283, 25.9015, 164.688" rotation="0.089619, 0.0896191, -0.701404, 0.701405" scale="1.0, 1.0, 1.0"/>
    <transform name="Bip02 Footsteps" translation="13.0869, -3.50969e-006, -50.3763" rotation="-0.089619, -0.0896191, 0.701404, 0.701405" scale="1.0, 1.0, 1.0"/>
    <transform name="Bip02 Pelvis" translation="-1.15583, 0.0, -1.79857e-006" rotation="-0.499999, -0.5, -0.5, 0.500001" scale="1.0, 1.0, 1.0"/>
    <transform name="Bip02 Spine" translation="9.85491, -0.00683108, -0.000497141" rotation="0.0371269, 0.00463014, -0.107592, 0.993491" scale="1.0, 1.0, 1.0"/>
    <transform name="Bip02 Spine1" translation="8.8159, -0.00880038, -0.000658576" rotation="0.0372418, -0.00132154, -0.0289249, 0.998887" scale="1.0, 1.0, 1.0"/>
    <transform name="Bip02 Spine2" translation="11.0999, -0.0110065, -0.00083385" rotation="0.0373547, 0.0011795, -0.100601, 0.994225" scale="1.0, 1.0, 1.0"/>
    <transform name="Bip02 Neck" translation="14.1484, -0.00528669, -2.00296e-007" rotation="0.0, 0.0, -0.0181963, 0.999834" scale="1.0, 1.0, 1.0"/>
    <transform name="Bip02 Head" translation="6.64598, -1.59467e-006, 1.42987e-007" rotation="-0.110338, -0.00554885, 0.255376, 0.960509" scale="1.0, 1.0, 1.0"/>
    <transform name="Bip02 HeadNub" translation="36.1861, 1.49063e-006, 0.0" rotation="0.0, 0.0, 0.0, 1.0" scale="1.0, 1.0, 1.0"/>
    <transform name="Bip02 Ponytail1" translation="20.4834, -7.4838, -11.0856" rotation="-0.00974229, -0.170458, 0.952406, -0.252532" scale="1.0, 1.0, 1.0"/>
    <transform name="Bip02 Ponytail11" translation="13.6603, -0.0101598, 0.000398229" rotation="-0.023701, -0.0247902, -0.214715, 0.976074" scale="1.0, 1.0, 1.0"/>
    <transform name="Bip02 Ponytail12" translation="14.0675, -0.00894234, 0.00041775" rotation="-0.0250157, -0.0212271, -0.0888816, 0.995502" scale="1.0, 1.0, 1.0"/>
    <transform name="Bip02 Ponytail13" translation="11.4296, -0.0160141, 0.00110248" rotation="-0.0314143, -0.015812, 0.131031, 0.990754" scale="1.0, 1.0, 1.0"/>
    <transform name="Bip02 Ponytail1Nub" translation="20.8677, 7.2768e-007, 2.43466e-007" rotation="0.707388, 0.706825, 9.87695e-007, -9.91797e-007" scale="1.0, 1.0, 1.0"/>
    <transform name="Bip02 Ponytail2" translation="21.3941, -5.36347, 12.0419" rotation="-0.037276, 0.102715, 0.98023, -0.164952" scale="1.0, 1.0, 1.0"/>
    <transform name="Bip02 Ponytail21" translation="14.6341, -0.0127015, -0.000648549" rotation="0.0271062, 0.0270905, -0.0614585, 0.997374" scale="1.0, 1.0, 1.0"/>
    <transform name="Bip02 Ponytail22" translation="16.0999, -0.0131487, -0.000419688" rotation="0.0169872, -0.0446402, 0.0224817, 0.998606" scale="1.0, 1.0, 1.0"/>
    <transform name="Bip02 Ponytail23" translation="16.5398, -0.0126423, -0.00059337" rotation="0.0272256, -0.0690017, 0.0556417, 0.995691" scale="1.0, 1.0, 1.0"/>
    <transform name="Bip02 Ponytail2Nub" translation="15.9971, -2.34217e-006, 3.22964e-007" rotation="0.707388, 0.706825, 9.88557e-007, -9.87346e-007" scale="1.0, 1.0, 1.0"/>
    <transform name="Bip02 L Clavicle" translation="-1.12056e-005, 0.00528102, 3.4594" rotation="0.436334, -0.00329652, 0.899525, -0.0213762" scale="1.0, 1.0, 1.0"/>
    <transform name="Bip02 L UpperArm" translation="14.6244, -6.15313e-007, -5.00584e-007" rotation="0.203565, 0.260082, -0.159627, 0.930289" scale="1.0, 1.0, 1.0"/>
    <transform name="Bip02 L Forearm" translation="27.0197, 1.07925e-006, 2.77388e-006" rotation="0.0, 0.0, -0.425248, 0.905077" scale="1.0, 1.0, 1.0"/>
    <transform name="Bip02 L Hand" translation="18.529, 6.16157e-006, -6.08752e-006" rotation="-0.706763, -0.0396097, 0.00184651, 0.706339" scale="1.0, 1.0, 1.0"/>
    <transform name="Bip02 L Finger0" translation="5.43344, -0.00308436, -6.39061" rotation="0.698709, 0.435563, -0.160159, 0.544463" scale="1.0, 1.0, 1.0"/>
    <transform name="Bip02 L Finger01" translation="4.86918, -2.44303e-006, 5.07413e-007" rotation="0.0, 0.0, 0.321439, 0.94693" scale="1.0, 1.0, 1.0"/>
    <transform name="Bip02 L Finger0Nub" translation="5.85088, 2.07402e-006, -3.03402e-006" rotation="0.0, 0.0, 0.0, 1.0" scale="1.0, 1.0, 1.0"/>
    <transform name="Bip02 L Finger1" translation="12.6299, -1.21083, -4.22834" rotation="0.0191197, 0.0579786, 0.318739, 0.945875" scale="1.0, 1.0, 1.0"/>
    <transform name="Bip02 L Finger11" translation="4.71211, -2.71753e-006, -6.60259e-006" rotation="0.0, 0.0, 0.378649, 0.925541" scale="1.0, 1.0, 1.0"/>
    <transform name="Bip02 L Finger1Nub" translation="5.46605, 1.18202e-006, 4.26328e-006" rotation="0.0, 0.0, 0.0, 1.0" scale="1.0, 1.0, 1.0"/>
    <transform name="Bip02 L Finger2" translation="13.5902, 0.516085, 2.76275" rotation="-0.161619, -0.00917245, 0.28424, 0.944988" scale="1.0, 1.0, 1.0"/>
    <transform name="Bip02 L Finger21" translation="4.71931, 0.0, -9.78337e-006" rotation="0.0, 0.0, 0.378649, 0.925541" scale="1.0, 1.0, 1.0"/>
    <transform name="Bip02 L Finger2Nub" translation="5.89014, -7.40321e-007, 9.3831e-007" rotation="0.0, 0.0, 0.0, 1.0" scale="1.0, 1.0, 1.0"/>
    <transform name="Bip02 R Clavicle" translation="-1.15306e-005, 0.00529838, -3.4594" rotation="-0.479124, -0.211198, 0.845967, 0.100872" scale="1.0, 1.0, 1.0"/>
    <transform name="Bip02 R UpperArm" translation="14.6244, -2.64898e-006, -5.89136e-006" rotation="-0.0504618, -0.286023, -0.0484022, 0.955668" scale="1.0, 1.0, 1.0"/>
    <transform name="Bip02 R Forearm" translation="27.0198, -8.23793e-007, 1.98682e-006" rotation="0.0, 0.0, -0.285711, 0.958316" scale="1.0, 1.0, 1.0"/>
    <transform name="Bip02 R Hand" translation="18.529, 1.2753e-006, -1.92822e-006" rotation="0.629108, 0.0355495, -0.0136629, 0.776384" scale="1.0, 1.0, 1.0"/>
    <transform name="Bip02 R Finger0" translation="5.43344, -0.00309012, 6.39061" rotation="-0.729385, -0.291153, -0.144267, 0.602009" scale="1.0, 1.0, 1.0"/>
    <transform name="Bip02 R Finger01" translation="4.86919, -1.43839e-006, 8.81017e-006" rotation="0.0, 0.0, 0.241922, 0.970296" scale="1.0, 1.0, 1.0"/>
    <transform name="Bip02 R Finger0Nub" translation="5.85087, -1.41525e-006, 7.60703e-006" rotation="0.0, 0.0, 1.0, 0.0" scale="1.0, 1.0, 1.0"/>
    <transform name="Bip02 R Finger1" translation="12.6299, -1.21084, 4.22834" rotation="-0.0239878, -0.0561397, 0.398133, 0.915294" scale="1.0, 1.0, 1.0"/>
    <transform name="Bip02 R Finger11" translation="4.71212, 1.33547e-006, -3.15796e-006" rotation="0.0, 0.0, 0.300706, 0.953717" scale="1.0, 1.0, 1.0"/>
    <transform name="Bip02 R Finger1Nub" translation="5.46605, -5.60043e-007, 6.32364e-006" rotation="0.0, 0.0, 1.0, 0.0" scale="1.0, 1.0, 1.0"/>
    <transform name="Bip02 R Finger2" translation="13.5902, 0.516076, -2.76274" rotation="0.136563, 0.0358429, 0.411391, 0.900457" scale="1.0, 1.0, 1.0"/>
    <transform name="Bip02 R Finger21" translation="4.71932, 1.43379e-006, -2.0589e-006" rotation="0.0, 0.0, 0.300706, 0.953717" scale="1.0, 1.0, 1.0"/>
    <transform name="Bip02 R Finger2Nub" translation="5.89015, 2.17232e-006, -2.74491e-006" rotation="0.0, 0.0, 1.0, 0.0" scale="1.0, 1.0, 1.0"/>
    <transform name="Bip02 L Thigh" translation="-9.78464, -1.43948, 9.08674" rotation="0.534074, 0.805207, 0.0517795, -0.252439" scale="1.0, 1.0, 1.0"/>
    <transform name="Bip02 L Calf" translation="27.795, -1.36415e-005, 2.01922e-006" rotation="0.0, 0.0, -0.5845, 0.811393" scale="1.0, 1.0, 1.0"/>
    <transform name="Bip02 L Foot" translation="29.6015, -1.40874e-006, -4.69426e-006" rotation="-0.0601756, -0.121981, 0.166199, 0.976667" scale="1.0, 1.0, 1.0"/>
    <transform name="Bip02 L Toe0" translation="14.534, 17.5771, 1.45185e-006" rotation="0.0, 0.0, 0.707107, 0.707107" scale="1.0, 1.0, 1.0"/>
    <transform name="Bip02 L Toe0Nub" translation="11.101, -4.60775e-006, -1.59704e-006" rotation="0.0, 0.0, 1.0, 0.0" scale="1.0, 1.0, 1.0"/>
    <transform name="Bip02 R Thigh" translation="-9.47093, -2.76752, -9.11064" rotation="0.517468, 0.776241, -0.180739, 0.311465" scale="1.0, 1.0, 1.0"/>
    <transform name="Bip02 R Calf" translation="27.795, -1.27211e-005, -4.81126e-006" rotation="0.0, 0.0, -0.666643, 0.745377" scale="1.0, 1.0, 1.0"/>
    <transform name="Bip02 R Foot" translation="29.6015, -3.68188e-006, 1.42141e-006" rotation="-0.0409516, 0.0456438, 0.230591, 0.971116" scale="1.0, 1.0, 1.0"/>
    <transform name="Bip02 R Toe0" translation="14.534, 17.5771, 1.74399e-007" rotation="0.0, 0.0, 0.707107, 0.707107" scale="1.0, 1.0, 1.0"/>
    <transform name="Bip02 R Toe0Nub" translation="11.101, -1.94317e-006, 4.41607e-007" rotation="0.0, 0.0, 0.0, 1.0" scale="1.0, 1.0, 1.0"/>
    <transform name="Bip02 Tail" translation="-2.95809, -9.74801, 0.656493" rotation="-0.0587538, 0.182728, 0.970667, -0.144787" scale="1.0, 1.0, 1.0"/>
    <transform name="Bip02 Tail1" translation="18.4159, -0.01336, 0.000314924" rotation="-0.00344752, -0.066678, 0.120591, 0.990454" scale="1.0, 1.0, 1.0"/>
    <transform name="Bip02 Tail2" translation="17.2806, -0.0157259, -0.000924093" rotation="0.0286943, 0.017756, 0.0339289, 0.998854" scale="1.0, 1.0, 1.0"/>
    <transform name="Bip02 TailNub" translation="19.829, 2.38944e-006, -2.2739e-006" rotation="0.707388, 0.706825, 9.74552e-007, -9.78779e-007" scale="1.0, 1.0, 1.0"/>
    <transform name="Bone01" translation="-1.02918, 10.6656, 0.0733637" rotation="0.634016, 0.425062, 0.273252, 0.585388" scale="1.0, 1.0, 1.0"/>
    <transform name="Bone02" translation="23.0916, 2.31199e-006, 2.50431e-006" rotation="0.0, 0.0, 0.0, 1.0" scale="1.0, 1.0, 1.0"/>
    <transform name="rider" translation="174.459, 3.32103, -13.7466" rotation="0.0, 0.0, 0.0, 1.0" scale="1.0, 1.0, 1.0"/>
  </frame>

  <frame>
    <transform name="bison" translation="-529.682, 341.794, -38.2763" rotation="0.0, 9.28547e-007, 0.0, 1.0" scale="35.5709, 28.4567, 28.4567"/>
    <transform name="Omni03" translation="-1642.78, -3829.81, -4202.06" rotation="0.0, 0.0, 0.0, 1.0" scale="34.5, 34.5, 34.5"/>
    <transform name="Omni05" translation="-3561.19, 3757.06, -2462.9" rotation="0.0, 0.0, 0.0, 1.0" scale="34.5, 34.5, 34.5"/>
    <transform name="Omni06" translation="4739.17, 2891.95, 11806.9" rotation="0.0, 0.0, 0.0, 1.0" scale="34.5, 34.5, 34.5"/>
    <transform name="Omni07" translation="13411.8, 5143.02, -2619.83" rotation="0.0, 0.0, 0.0, 1.0" scale="34.5, 34.5, 34.5"/>
    <transform name="Omni08" translation="-18659.1, 6889.32, 1469.94" rotation="0.0, 0.0, 0.0, 1.0" scale="34.5, 34.5, 34.5"/>
    <transform name="Omni09" translation="2752.18, -15860.6, 10088.9" rotation="0.0, 0.0, 0.0, 1.0" scale="34.5, 34.5, 34.5"/>
    <transform name="Bip01" translation="-0.165565, 88.3778, 92.7077" rotation="0.500004, 0.499996, -0.499996, 0.500004" scale="1.0, 1.0, 1.0"/>
    <transform name="Bip01 Footsteps" translation="95.0747, -0.00151307, 7.53358e-006" rotation="-0.500004, -0.499996, 0.499996, 0.500004" scale="1.0, 1.0, 1.0"/>
    <transform name="Bip01 Pelvis" translation="14.9214, -1.06976, 1.22794e-006" rotation="0.507973, 0.507973, 0.491898, -0.491898" scale="1.0, 1.0, 1.0"/>
    <transform name="Bip01 Spine" translation="23.8972, -1.44248, -0.768878" rotation="-0.00159528, 0.000388503, -0.21701, 0.976168" scale="1.0, 1.0, 1.0"/>
    <transform name="Bip01 Spine1" translation="35.5313, -0.0275591, 1.93886e-005" rotation="-0.000820243, 0.00417099, 0.113554, 0.993523" scale="1.0, 1.0, 1.0"/>
    <transform name="Bip01 Spine2" translation="35.5308, -0.0259571, -0.000109728" rotation="0.000674341, 0.0125489, 0.111003, 0.993741" scale="1.0, 1.0, 1.0"/>
    <transform name="Bip01 Neck" translation="33.4196, -0.01051, 0.0" rotation="0.0, -2.65568e-007, 0.0957562, 0.995405" scale="1.0, 1.0, 1.0"/>
    <transform name="Bip01 Neck1" translation="13.4452, -0.0101369, 0.0" rotation="0.0, -4.52508e-007, 0.163161, 0.9866" scale="1.0, 1.0, 1.0"/>
    <transform name="Bip01 Head" translation="13.4417, 3.56475e-006, 0.0" rotation="-0.00726354, 0.000482803, -0.286913, 0.957929" scale="1.0, 1.0, 1.0"/>
    <transform name="Bip01 HeadNub" translation="41.8745, -2.79646e-006, 0.0" rotation="0.0, 0.0, 0.0, 1.0" scale="1.0, 1.0, 1.0"/>
    <transform name="Bip01 Ponytail1" translation="1.85123, 47.5259, 0.000136834" rotation="0.0418741, -0.0297012, 0.812568, 0.580601" scale="1.0, 1.0, 1.0"/>
    <transform name="Bip01 Ponytail11" translation="12.6818, -0.00940036, -4.26271e-006" rotation="0.00969103, -0.0504143, 0.185085, 0.981381" scale="1.0, 1.0, 1.0"/>
    <transform name="Bip01 Ponytail1Nub" translation="12.6781, 1.30644e-006, 4.40064e-007" rotation="0.707388, 0.706825, 9.85961e-007, -9.79889e-007" scale="1.0, 1.0, 1.0"/>
    <transform name="Bip01 L Clavicle" translation="-8.76419, 1.27223, 32.4074" rotation="0.488409, 0.468974, 0.610616, 0.410692" scale="1.0, 1.0, 1.0"/>
    <transform name="Bip01 L UpperArm" translation="33.0219, -8.11892e-007, 1.03088e-006" rotation="-0.702104, 0.104393, -0.0402871, 0.703227" scale="1.0, 1.0, 1.0"/>
    <transform name="Bip01 L Forearm" translation="22.361, -1.54928e-007, -1.24922e-006" rotation="0.0, 0.0, -0.24859, 0.968609" scale="1.0, 1.0, 1.0"/>
    <transform name="Bip01 L Hand" translation="31.134, -3.3261e-007, -1.74608e-006" rotation="-0.0318739, -0.000125431, 0.162079, 0.986263" scale="1.0, 1.0, 1.0"/>
    <transform name="Bip01 L Finger0" translation="12.825, -0.714871, -4.0374" rotation="0.0248638, 0.0074394, -0.147571, 0.988711" scale="1.0, 1.0, 1.0"/>
    <transform name="Bip01 L Finger0Nub" translation="9.28433, 0.0, 2.082e-006" rotation="0.0, 0.0, 0.0, 1.0" scale="1.0, 1.0, 1.0"/>
    <transform name="Bip01 R Clavicle" translation="-8.76419, 1.27241, -32.4074" rotation="0.5977, 0.352317, -0.578707, -0.428632" scale="1.0, 1.0, 1.0"/>
    <transform name="Bip01 R UpperArm" translation="33.0219, -6.28203e-006, -3.2421e-006" rotation="0.619945, -0.221872, -0.0159262, 0.752454" scale="1.0, 1.0, 1.0"/>
    <transform name="Bip01 R Forearm" translation="22.3611, 1.3868e-006, 1.03816e-006" rotation="0.0, 0.0, -0.371274, 0.928523" scale="1.0, 1.0, 1.0"/>
    <transform name="Bip01 R Hand" translation="31.134, 3.05694e-006, 1.3021e-006" rotation="0.0268987, 0.0110725, -0.00368805, 0.99957" scale="1.0, 1.0, 1.0"/>
    <transform name="Bip01 R Finger0" translation="12.825, -0.714872, 4.0374" rotation="0.0460875, -0.00113131, 0.179589, 0.982661" scale="1.0, 1.0, 1.0"/>
    <transform name="Bip01 R Finger0Nub" translation="9.28433, 3.2019e-007, 6.13438e-007" rotation="0.0, 0.0, 1.0, 0.0" scale="1.0, 1.0, 1.0"/>
    <transform name="Bip01 L Thigh" translation="-22.2589, -8.88477, 20.3" rotation="0.740248, 0.672066, -0.0182069, 0.00533002" scale="1.0, 1.0, 1.0"/>
    <transform name="Bip01 L Calf" translation="44.7054, -1.91207e-006, 1.42914e-006" rotation="0.0, 0.0, -0.422261, 0.906474" scale="1.0, 1.0, 1.0"/>
    <transform name="Bip01 L HorseLink" translation="25.1575, 7.52541e-006, -1.81936e-006" rotation="0.0, 0.0, 0.681674, 0.731656" scale="1.0, 1.0, 1.0"/>
    <transform name="Bip01 L Foot" translation="19.0106, -6.41939e-007, 3.69105e-007" rotation="0.00425388, 0.00734604, -0.537764, 0.843053" scale="1.0, 1.0, 1.0"/>
    <transform name="Bip01 L Toe0" translation="7.55725, 12.3023, 1.8591e-006" rotation="0.0, 0.0, 0.707107, 0.707107" scale="1.0, 1.0, 1.0"/>
    <transform name="Bip01 L Toe0Nub" translation="1.13738, 0.0, -6.5642e-007" rotation="0.0, 0.0, 1.0, 0.0" scale="1.0, 1.0, 1.0"/>
    <transform name="Bip01 R Thigh" translation="-22.2562, -8.75634, -18.8231" rotation="0.567702, 0.822899, -0.0225015, -0.00672265" scale="1.0, 1.0, 1.0"/>
    <transform name="Bip01 R Calf" translation="44.7054, 3.94571e-006, -1.15336e-006" rotation="0.0, 0.0, -0.512269, 0.858825" scale="1.0, 1.0, 1.0"/>
    <transform name="Bip01 R HorseLink" translation="25.1575, -1.25848e-006, 7.15022e-007" rotation="0.0, 0.0, 0.817896, 0.575367" scale="1.0, 1.0, 1.0"/>
    <transform name="Bip01 R Foot" translation="19.0106, 3.31066e-006, 1.71634e-006" rotation="-0.0023389, 0.0119655, -0.421466, 0.906762" scale="1.0, 1.0, 1.0"/>
    <transform name="Bip01 R Toe0" translation="7.55724, 12.3023, -3.68783e-007" rotation="0.0, 0.0, 0.707107, 0.707107" scale="1.0, 1.0, 1.0"/>
    <transform name="Bip01 R Toe0Nub" translation="1.13738, 0.0, -2.95976e-007" rotation="0.0, 0.0, 0.0, 1.0" scale="1.0, 1.0, 1.0"/>
    <transform name="Bip01 Tail" translation="-37.6898, -22.6031, 1.32939" rotation="-0.0491475, 0.0436918, 0.930237, 0.361019" scale="1.0, 1.0, 1.0"/>
    <transform name="Bip01 Tail1" translation="12.2182, -0.00843277, -0.000122462" rotation="-0.010198, -0.0624714, -0.257184, 0.964287" scale="1.0, 1.0, 1.0"/>
    <transform name="Bip01 Tail2" translation="12.2272, -0.0103428, 0.0017933" rotation="-0.0620616, -0.0970754, 0.196143, 0.973783" scale="1.0, 1.0, 1.0"/>
    <transform name="Bip01 Tail3" translation="14.1796, -0.0115105, -2.61518e-005" rotation="0.001099, 0.000288051, 0.0387105, 0.99925" scale="1.0, 1.0, 1.0"/>
    <transform name="Bip01 TailNub" translation="14.4946, -9.86533e-007, -7.07509e-007" rotation="0.707388, 0.706825, 9.78859e-007, -9.80111e-007" scale="1.0, 1.0, 1.0"/>
    <transform name="Bip02" translation="0.696283, 25.7588, 166.345" rotation="0.0677731, 0.0677732, -0.703851, 0.703852" scale="1.0, 1.0, 1.0"/>
    <transform name="Bip02 Footsteps" translation="9.96979, -1.74659e-006, -51.2901" rotation="-0.0677731, -0.0677732, 0.703851, 0.703852" scale="1.0, 1.0, 1.0"/>
    <transform name="Bip02 Pelvis" translation="-1.15582, 0.0, -1.2107e-005" rotation="-0.499999, -0.5, -0.5, 0.500001" scale="1.0, 1.0, 1.0"/>
    <transform name="Bip02 Spine" translation="9.8561, -0.00697096, -0.000678845" rotation="0.0493713, -0.00109767, -0.0213906, 0.998551" scale="1.0, 1.0, 1.0"/>
    <transform name="Bip02 Spine1" translation="8.81458, -0.00860531, -0.00086248" rotation="0.0493402, 0.00211517, -0.104401, 0.993308" scale="1.0, 1.0, 1.0"/>
    <transform name="Bip02 Spine2" translation="11.1021, -0.0112143, -0.00111189" rotation="0.0493855, -3.93242e-005, 0.0, 0.99878" scale="1.0, 1.0, 1.0"/>
    <transform name="Bip02 Neck" translation="14.1492, -0.00525984, 0.0" rotation="0.0, -1.50918e-007, 0.0542433, 0.998528" scale="1.0, 1.0, 1.0"/>
    <transform name="Bip02 Head" translation="6.64599, 3.38013e-007, 4.06035e-007" rotation="-0.146738, 0.0103717, 0.0806431, 0.985828" scale="1.0, 1.0, 1.0"/>
    <transform name="Bip02 HeadNub" translation="36.1861, 3.26169e-006, 0.0" rotation="0.0, 0.0, 0.0, 1.0" scale="1.0, 1.0, 1.0"/>
    <transform name="Bip02 Ponytail1" translation="20.4849, -7.4831, -11.0855" rotation="-0.0143714, -0.171508, 0.969247, -0.175894" scale="1.0, 1.0, 1.0"/>
    <transform name="Bip02 Ponytail11" translation="13.6622, -0.0108281, 0.000653911" rotation="-0.0300862, -0.00512465, -0.12662, 0.991482" scale="1.0, 1.0, 1.0"/>
    <transform name="Bip02 Ponytail12" translation="14.0668, -0.00877764, 0.000535071" rotation="-0.0300862, -0.00512464, -0.12662, 0.991482" scale="1.0, 1.0, 1.0"/>
    <transform name="Bip02 Ponytail13" translation="11.4211, -0.016051, 0.000969128" rotation="-0.0300862, -0.00512464, -0.126621, 0.991482" scale="1.0, 1.0, 1.0"/>
    <transform name="Bip02 Ponytail1Nub" translation="20.8677, -1.19392e-006, -3.42008e-007" rotation="0.707388, 0.706825, 9.76984e-007, -9.71171e-007" scale="1.0, 1.0, 1.0"/>
    <transform name="Bip02 Ponytail2" translation="21.3931, -5.36378, 12.0422" rotation="-0.00267444, 0.0952663, 0.974017, -0.205445" scale="1.0, 1.0, 1.0"/>
    <transform name="Bip02 Ponytail21" translation="14.6344, -0.0127507, -3.92872e-007" rotation="0.0, 1.39615e-007, -0.0498082, 0.998759" scale="1.0, 1.0, 1.0"/>
    <transform name="Bip02 Ponytail22" translation="16.0957, -0.0126835, 0.0" rotation="0.0, 3.78123e-007, -0.136666, 0.990617" scale="1.0, 1.0, 1.0"/>
    <transform name="Bip02 Ponytail23" translation="16.5361, -0.0125307, -1.18607e-006" rotation="0.0, 2.48102e-007, -0.0889809, 0.996033" scale="1.0, 1.0, 1.0"/>
    <transform name="Bip02 Ponytail2Nub" translation="15.9972, -3.1548e-006, -3.06367e-007" rotation="0.707388, 0.706825, 9.77321e-007, -9.76843e-007" scale="1.0, 1.0, 1.0"/>
    <transform name="Bip02 L Clavicle" translation="1.09901e-006, 0.00528455, 3.4594" rotation="0.508337, -0.221906, 0.828485, -0.0772206" scale="1.0, 1.0, 1.0"/>
    <transform name="Bip02 L UpperArm" translation="14.6244, 2.77211e-006, -8.83452e-007" rotation="0.269043, 0.233093, -0.190153, 0.914946" scale="1.0, 1.0, 1.0"/>
    <transform name="Bip02 L Forearm" translation="27.0198, 3.85838e-007, 1.41656e-006" rotation="0.0, 0.0, -0.613483, 0.789708" scale="1.0, 1.0, 1.0"/>
    <transform name="Bip02 L Hand" translation="18.529, 4.28325e-006, -2.05376e-006" rotation="-0.706826, -0.0370071, 1.47249e-005, 0.706419" scale="1.0, 1.0, 1.0"/>
    <transform name="Bip02 L Finger0" translation="5.43344, -0.00308171, -6.3906" rotation="0.676539, 0.398831, -0.234261, 0.573018" scale="1.0, 1.0, 1.0"/>
    <transform name="Bip02 L Finger01" translation="4.86918, 3.45768e-006, 1.40944e-006" rotation="0.0, 0.0, 0.321439, 0.94693" scale="1.0, 1.0, 1.0"/>
    <transform name="Bip02 L Finger0Nub" translation="5.85088, 1.28717e-006, -6.40694e-006" rotation="0.0, 0.0, 0.0, 1.0" scale="1.0, 1.0, 1.0"/>
    <transform name="Bip02 L Finger1" translation="12.6299, -1.21084, -4.22834" rotation="0.0151588, 0.0591379, 0.254104, 0.965248" scale="1.0, 1.0, 1.0"/>
    <transform name="Bip02 L Finger11" translation="4.71211, 7.4241e-007, -2.81503e-006" rotation="0.0, 0.0, 0.378649, 0.925541" scale="1.0, 1.0, 1.0"/>
    <transform name="Bip02 L Finger1Nub" translation="5.46605, -3.25145e-007, -9.77348e-007" rotation="0.0, 0.0, 0.0, 1.0" scale="1.0, 1.0, 1.0"/>
    <transform name="Bip02 L Finger2" translation="13.5902, 0.516084, 2.76275" rotation="-0.161355, -0.013016, 0.261671, 0.951485" scale="1.0, 1.0, 1.0"/>
    <transform name="Bip02 L Finger21" translation="4.71933, 2.05711e-006, 7.07216e-006" rotation="0.0, 0.0, 0.378649, 0.925541" scale="1.0, 1.0, 1.0"/>
    <transform name="Bip02 L Finger2Nub" translation="5.89014, 1.05205e-006, -5.21409e-006" rotation="0.0, 0.0, 0.0, 1.0" scale="1.0, 1.0, 1.0"/>
    <transform name="Bip02 R Clavicle" translation="5.51792e-006, 0.00530182, -3.4594" rotation="-0.535027, -0.0592381, 0.8366, 0.101675" scale="1.0, 1.0, 1.0"/>
    <transform name="Bip02 R UpperArm" translation="14.6244, -2.57002e-006, -8.19649e-006" rotation="-0.071063, -0.277951, -0.0744011, 0.955069" scale="1.0, 1.0, 1.0"/>
    <transform name="Bip02 R Forearm" translation="27.0197, 1.29127e-006, 7.73919e-007" rotation="0.0, 0.0, -0.409249, 0.912423" scale="1.0, 1.0, 1.0"/>
    <transform name="Bip02 R Hand" translation="18.529, 2.97505e-006, 3.93612e-007" rotation="0.559048, 0.0363244, 0.00707575, 0.828309" scale="1.0, 1.0, 1.0"/>
    <transform name="Bip02 R Finger0" translation="5.43344, -0.00308175, 6.3906" rotation="-0.722809, -0.307113, -0.157463, 0.598693" scale="1.0, 1.0, 1.0"/>
    <transform name="Bip02 R Finger01" translation="4.86918, -3.39769e-006, -1.32497e-005" rotation="0.0, 0.0, 0.241922, 0.970296" scale="1.0, 1.0, 1.0"/>
    <transform name="Bip02 R Finger0Nub" translation="5.85088, 1.52855e-006, 5.74323e-006" rotation="0.0, 0.0, 1.0, 0.0" scale="1.0, 1.0, 1.0"/>
    <transform name="Bip02 R Finger1" translation="12.6299, -1.21083, 4.22834" rotation="-0.0227481, -0.0566534, 0.37792, 0.923823" scale="1.0, 1.0, 1.0"/>
    <transform name="Bip02 R Finger11" translation="4.71212, -6.07281e-007, 3.46589e-006" rotation="0.0, 0.0, 0.300706, 0.953717" scale="1.0, 1.0, 1.0"/>
    <transform name="Bip02 R Finger1Nub" translation="5.46605, -1.31018e-006, -3.94258e-006" rotation="0.0, 0.0, 1.0, 0.0" scale="1.0, 1.0, 1.0"/>
    <transform name="Bip02 R Finger2" translation="13.5902, 0.516087, -2.76275" rotation="0.161674, -0.00815646, 0.383626, 0.90919" scale="1.0, 1.0, 1.0"/>
    <transform name="Bip02 R Finger21" translation="4.71933, 7.24497e-007, -2.62035e-006" rotation="0.0, 0.0, 0.300706, 0.953717" scale="1.0, 1.0, 1.0"/>
    <transform name="Bip02 R Finger2Nub" translation="5.89014, -2.18626e-006, -2.90868e-006" rotation="0.0, 0.0, 1.0, 0.0" scale="1.0, 1.0, 1.0"/>
    <transform name="Bip02 L Thigh" translation="-9.84665, 0.487115, 9.12215" rotation="0.557434, 0.77337, 0.0995306, -0.285062" scale="1.0, 1.0, 1.0"/>
    <transform name="Bip02 L Calf" translation="27.795, 6.9625e-006, -6.52985e-007" rotation="0.0, 0.0, -0.651372, 0.758759" scale="1.0, 1.0, 1.0"/>
    <transform name="Bip02 L Foot" translation="29.6015, 1.36536e-006, 2.93996e-006" rotation="0.0447198, -0.153836, 0.027393, 0.986704" scale="1.0, 1.0, 1.0"/>
    <transform name="Bip02 L Toe0" translation="14.534, 17.5771, -1.23503e-006" rotation="0.0, 0.0, 0.707107, 0.707107" scale="1.0, 1.0, 1.0"/>
    <transform name="Bip02 L Toe0Nub" translation="11.101, 6.05275e-006, -2.32894e-006" rotation="0.0, 0.0, 1.0, 0.0" scale="1.0, 1.0, 1.0"/>
    <transform name="Bip02 R Thigh" translation="-9.84808, -1.31306, -9.03732" rotation="0.513327, 0.769779, -0.239889, 0.293921" scale="1.0, 1.0, 1.0"/>
    <transform name="Bip02 R Calf" translation="27.795, -7.54232e-006, -6.34761e-007" rotation="0.0, 0.0, -0.682267, 0.731103" scale="1.0, 1.0, 1.0"/>
    <transform name="Bip02 R Foot" translation="29.6015, 1.4278e-006, -1.93881e-006" rotation="0.0450013, -0.0206602, -0.0345183, 0.998177" scale="1.0, 1.0, 1.0"/>
    <transform name="Bip02 R Toe0" translation="14.534, 17.5771, -2.00427e-006" rotation="0.0, 0.0, 0.707107, 0.707107" scale="1.0, 1.0, 1.0"/>
    <transform name="Bip02 R Toe0Nub" translation="11.101, 3.59586e-006, -4.86151e-007" rotation="0.0, 0.0, 0.0, 1.0" scale="1.0, 1.0, 1.0"/>
    <transform name="Bip02 Tail" translation="-4.59095, -9.07388, 0.896094" rotation="-0.035925, 0.200003, 0.977197, -0.0615955" scale="1.0, 1.0, 1.0"/>
    <transform name="Bip02 Tail1" translation="18.4178, -0.0127198, 0.000655792" rotation="-0.0024415, -0.11063, 0.194376, 0.974666" scale="1.0, 1.0, 1.0"/>
    <transform name="Bip02 Tail2" translation="17.2821, -0.0155871, 5.96291e-005" rotation="0.0015775, -0.0435159, 0.0799868, 0.995844" scale="1.0, 1.0, 1.0"/>
    <transform name="Bip02 TailNub" translation="19.829, -1.04406e-005, -2.06084e-006" rotation="0.707388, 0.706825, 9.7204e-007, -9.85153e-007" scale="1.0, 1.0, 1.0"/>
    <transform name="Bone01" translation="-1.02918, 10.6656, 0.0733637" rotation="0.634016, 0.425062, 0.273252, 0.585388" scale="1.0, 1.0, 1.0"/>
    <transform name="Bone02" translation="23.0916, 5.17118e-006, 4.95002e-006" rotation="0.0, 0.0, 0.0, 1.0" scale="1.0, 1.0, 1.0"/>
    <transform name="rider" translation="174.459, 3.32103, -13.7466" rotation="0.0, 0.0, 0.0, 1.0" scale="1.0, 1.0, 1.0"/>
  </frame>

</animation>
