<?xml version="1.0" standalone="yes"?>

<tutorial ident="forklift" board="Controls" players="2">

  <!-- show them a unit and have them click to select it -->
  <add_piece what="unit" id="1000" type="boom_town/forklift"
             location="16,16" owner="0"/>
  <center_on what="piece" id="1000"/>
  
  <!-- add an enemy unit and show them how to shoot it -->
  <add_piece what="unit" id="1001" type="frontier_town/artillery"
             location="1000" owner="1"/>
  <center_on what="piece" id="1001"/>
  <text message="click_to_highlight_attacks" step="4"/>
  <wait event="unit_selected" allowAttack="true"/>

  <text message="click_to_attack"/>
  <wait event="effect:bang" allowAttack="true"/>

  <text message="move_and_attack"/>
  <wait event="text_clicked"/>
  <text message="move_and_attack2"/>
  <wait event="effect:bang" allowAttack="true"/>

  <text message="move_double_click"/>
  <wait event="text_clicked"/>

  <!-- explain damage and unit respawnning -->
  <text message="damage_and_respawn" step="5"/>
  <wait event="text_clicked"/>
  <text message="damage_and_respawn2"/>
  <wait event="text_clicked"/>
  <text message="damage_and_respawn3"/>
  <wait event="text_clicked"/>

  <!-- wrap up and end the tutorial -->
  <text message="done"/>
  <wait event="text_clicked"/>

</tutorial>
